// converted by version  [v3.1.0]
// on Mon May 01 16:19:42 CEST 2023

.package applet {
	.aid 0x1:0xFF:0xFF:0x4:0x5:0x6:0x7:0x8:0x9;
	.version 0.1;

	.imports {
		0xA0:0x0:0x0:0x0:0x62:0x0:0x1 1.0;		//java/lang
		0xA0:0x0:0x0:0x0:0x62:0x1:0x1 1.5;		//javacard/framework
		0xA0:0x0:0x0:0x0:0x62:0x1:0x2 1.5;		//javacard/security
	}

	.applet {
		0x1:0xFF:0xFF:0x4:0x5:0x6:0x7:0x8:0x9:0x1:0x2 MainApplet;
	}

	.constantPool {
		// 0
		instanceFieldRef byte[] ArrayInDisguise/array;
		// 1
		instanceFieldRef short ArrayInDisguise/offset;
		// 2
		instanceFieldRef short GeneralMap/map_start;
		// 3
		instanceFieldRef short GeneralMap/map_size;
		// 4
		instanceFieldRef PSBTKey PSBTKeyPair/key;
		// 5
		instanceFieldRef short PSBTKey/start;
		// 6
		instanceFieldRef short GlobalUnsignedTXInput/previous_output_start;
		// 7
		instanceFieldRef short GlobalUnsignedTXInput/size;
		// 8
		instanceFieldRef short GlobalUnsignedTXOutput/valueStart;
		// 9
		instanceFieldRef short GlobalUnsignedTXOutput/size;
		// 10
		instanceFieldRef short GeneralMap/NUM_OF_KEYPAIR;
		// 11
		instanceFieldRef short GeneralMap/currentKeyPair;
		// 12
		instanceFieldRef PSBTKeyPair[] GeneralMap/keyPairs;
		// 13
		instanceFieldRef short GlobalMap/input_maps_total;
		// 14
		instanceFieldRef short GlobalMap/outputMapsTotal;
		// 15
		instanceFieldRef GlobalUnsignedTX GlobalMap/globalUnsignedTX;
		// 16
		instanceFieldRef short PSBTKey/keyKype;
		// 17
		instanceFieldRef PSBTValue PSBTKeyPair/value;
		// 18
		instanceFieldRef short PSBTValue/value_len_bytes;
		// 19
		instanceFieldRef short GlobalUnsignedTX/start;
		// 20
		instanceFieldRef short GlobalUnsignedTX/version;
		// 21
		instanceFieldRef short GlobalUnsignedTX/size;
		// 22
		instanceFieldRef short GlobalUnsignedTX/input_count;
		// 23
		instanceFieldRef GlobalUnsignedTXInput[] GlobalUnsignedTX/inputs;
		// 24
		instanceFieldRef short GlobalUnsignedTX/output_count;
		// 25
		instanceFieldRef GlobalUnsignedTXOutput[] GlobalUnsignedTX/outputs;
		// 26
		instanceFieldRef short GlobalUnsignedTX/lockTimeStart;
		// 27
		instanceFieldRef short GlobalUnsignedTXInput/script_size_start;
		// 28
		instanceFieldRef short GlobalUnsignedTXInput/script_size;
		// 29
		instanceFieldRef short GlobalUnsignedTXInput/script_sig_start;
		// 30
		instanceFieldRef short GlobalUnsignedTXInput/sequence_start;
		// 31
		instanceFieldRef short GlobalUnsignedTXOutput/script_size_start;
		// 32
		instanceFieldRef short GlobalUnsignedTXOutput/script_size;
		// 33
		instanceFieldRef short GlobalUnsignedTXOutput/script_pub_key_start;
		// 34
		instanceFieldRef GlobalMap PSBT/globalMap;
		// 35
		instanceFieldRef GeneralMap[] PSBT/input_maps;
		// 36
		instanceFieldRef GeneralMap[] PSBT/outputMaps;
		// 37
		instanceFieldRef PSBTKeyPair[] GeneralMap/keyPairs;
		// 38
		instanceFieldRef short GeneralMap/map_size;
		// 39
		instanceFieldRef short PSBTKey/key_len;
		// 40
		instanceFieldRef short PSBTKey/key_len_bytes;
		// 41
		instanceFieldRef short PSBTKeyPair/start;
		// 42
		instanceFieldRef short PSBTValue/start;
		// 43
		instanceFieldRef short PSBTValue/value_len;
		// 44
		virtualMethodRef 1.10.8(SS)V;		// setOutgoingAndSend(SS)V
		// 45
		.classRef GlobalUnsignedTX;
		// 46
		staticMethodRef GlobalUnsignedTXInput/<init>()V;
		// 47
		staticMethodRef GlobalUnsignedTXOutput/<init>()V;
		// 48
		virtualMethodRef GlobalUnsignedTX/getCount()S;
		// 49
		staticMethodRef Tools/byteSizeOfCWI(S)S;
		// 50
		virtualMethodRef GlobalUnsignedTXInput/fill(S)V;
		// 51
		virtualMethodRef GlobalUnsignedTXOutput/fill(S)V;
		// 52
		staticMethodRef Tools/compactWeirdoInt(S)S;
		// 53
		virtualMethodRef GlobalUnsignedTXInput/reset()V;
		// 54
		virtualMethodRef GlobalUnsignedTXOutput/reset()V;
		// 55
		staticMethodRef GlobalUnsignedTX/<init>()V;
		// 56
		virtualMethodRef PSBTKeyPair/getSize()S;
		// 57
		staticMethodRef 0.0.0()V;		// java/lang/Object.<init>()V
		// 58
		.classRef PSBTKeyPair;
		// 59
		virtualMethodRef 1.10.1()[B;		// getBuffer()[B
		// 60
		virtualMethodRef GlobalUnsignedTX/fill(S)V;
		// 61
		virtualMethodRef PSBTValue/getByte(S)B;
		// 62
		.classRef MainApplet;
		// 63
		staticMethodRef MainApplet/<init>([BSB)V;
		// 64
		staticMethodRef 1.3.0()V;		// javacard/framework/Applet.<init>()V
		// 65
		.classRef PSBT;
		// 66
		staticMethodRef PSBT/<init>()V;
		// 67
		staticFieldRef PSBT MainApplet/psbt;
		// 68
		.classRef ArrayInDisguise;
		// 69
		staticFieldRef ArrayInDisguise[] MainApplet/privDataStorage;
		// 70
		staticFieldRef ArrayInDisguise[] MainApplet/pubDataStorage;
		// 71
		staticMethodRef ArrayInDisguise/<init>(S)V;
		// 72
		staticFieldRef byte[] MainApplet/policy;
		// 73
		staticFieldRef byte[] MainApplet/totalOutput;
		// 74
		staticFieldRef short MainApplet/transactionOffset;
		// 75
		staticFieldRef short MainApplet/policyOffset;
		// 76
		staticFieldRef short MainApplet/policyUploadLocked;
		// 77
		virtualMethodRef 1.3.1()V;		// register()V
		// 78
		.classRef 0.2;		// java/lang/Exception
		// 79
		virtualMethodRef PSBT/reset()V;
		// 80
		virtualMethodRef PSBT/fill()V;
		// 81
		staticMethodRef 1.7.1(S)V;		// javacard/framework/ISOException.throwIt(S)V
		// 82
		virtualMethodRef MainApplet/checkStorageUsage()Z;
		// 83
		staticMethodRef FromApplet/send_data(Ljavacard/framework/APDU;[BSS)V;
			.descriptor	Ljavacard/framework/APDU;	1.10;

		// 84
		staticMethodRef FromApplet/send_data(Ljavacard/framework/APDU;S)V;
			.descriptor	Ljavacard/framework/APDU;	1.10;

		// 85
		staticFieldRef short PSBT/byte_size;
		// 86
		staticFieldRef short GlobalMap/PSBTversion;
		// 87
		staticFieldRef short PSBT/current_input_map;
		// 88
		staticFieldRef short PSBT/current_output_map;
		// 89
		virtualMethodRef MainApplet/validatePolicy()S;
		// 90
		staticMethodRef FromApplet/send_data(Ljavacard/framework/APDU;Lapplet/GlobalUnsignedTXInput;)V;
			.descriptor	Ljavacard/framework/APDU;	1.10;

		// 91
		virtualMethodRef GlobalUnsignedTX/reset()V;
		// 92
		staticMethodRef FromApplet/send_data(Ljavacard/framework/APDU;Lapplet/GeneralMap;)V;
			.descriptor	Ljavacard/framework/APDU;	1.10;

		// 93
		staticMethodRef FromApplet/send_data(Ljavacard/framework/APDU;Lapplet/GlobalUnsignedTXOutput;)V;
			.descriptor	Ljavacard/framework/APDU;	1.10;

		// 94
		staticMethodRef PSBTKeyPair/<init>()V;
		// 95
		staticFieldRef byte[] MainApplet/PSBTdata;
		// 96
		staticMethodRef FromApplet/send_data(Ljavacard/framework/APDU;Lapplet/PSBTKeyPair;)V;
			.descriptor	Ljavacard/framework/APDU;	1.10;

		// 97
		staticMethodRef Policy/validateTotalOutput(BS)Z;
		// 98
		staticMethodRef Policy/validateValueOwSS(BBS)Z;
		// 99
		staticMethodRef SetAndVerify/verifyECDSA([BS[BS)Z;
		// 100
		staticMethodRef SetAndVerify/setPublicKey([BS)V;
		// 101
		staticMethodRef 1.16.0([BS[BSS)B;		// javacard/framework/Util.arrayCompare([BS[BSS)B
		// 102
		staticMethodRef MainApplet/validationReturnProcedure(S)S;
		// 103
		.classRef GlobalMap;
		// 104
		staticMethodRef GlobalMap/<init>()V;
		// 105
		.classRef GeneralMap;
		// 106
		virtualMethodRef GlobalMap/fill(S)V;
		// 107
		virtualMethodRef PSBTKeyPair/fill(S)V;
		// 108
		virtualMethodRef GeneralMap/fill(S)V;
		// 109
		staticMethodRef Tools/getTotalOutput()V;
		// 110
		virtualMethodRef GlobalMap/reset()V;
		// 111
		virtualMethodRef GeneralMap/reset()V;
		// 112
		virtualMethodRef PSBTKeyPair/reset()V;
		// 113
		.classRef GlobalUnsignedTXInput;
		// 114
		staticMethodRef GeneralMap/<init>()V;
		// 115
		.classRef PSBTKey;
		// 116
		staticMethodRef PSBTKey/<init>()V;
		// 117
		.classRef PSBTValue;
		// 118
		staticMethodRef PSBTValue/<init>()V;
		// 119
		virtualMethodRef PSBTKey/fill(S)V;
		// 120
		virtualMethodRef PSBTKey/getSize()S;
		// 121
		virtualMethodRef PSBTValue/fill(S)V;
		// 122
		virtualMethodRef PSBTValue/getSize()S;
		// 123
		virtualMethodRef PSBTKey/reset()V;
		// 124
		virtualMethodRef PSBTValue/reset()V;
		// 125
		staticMethodRef 1.16.2([BS[BSS)S;		// javacard/framework/Util.arrayCopyNonAtomic([BS[BSS)S
		// 126
		.classRef GlobalUnsignedTXOutput;
		// 127
		staticMethodRef Tools/littleEndianCompareArrays([BS[BSS)S;
		// 128
		staticMethodRef Policy/checkItself(BSBSS)Z;
		// 129
		staticMethodRef 2.13.0(BSZ)Ljavacard/security/Key;;		// javacard/security/KeyBuilder.buildKey(BSZ)Ljavacard/security/Key;
			.descriptor	Ljavacard/security/Key;	2.0;

		// 130
		.classRef 2.19;		// javacard/security/ECPublicKey
		// 131
		staticFieldRef 2.19 SetAndVerify/publicKey;
		// 132
		staticMethodRef 2.15.0(BZ)Ljavacard/security/Signature;;		// javacard/security/Signature.getInstance(BZ)Ljavacard/security/Signature;
			.descriptor	Ljavacard/security/Signature;	2.15;

		// 133
		staticFieldRef 2.15 SetAndVerify/signEngine;
		// 134
		staticFieldRef byte[] SecP256k1/p;
		// 135
		staticFieldRef byte[] SecP256k1/a;
		// 136
		staticFieldRef byte[] SecP256k1/b;
		// 137
		staticFieldRef byte[] SecP256k1/G;
		// 138
		staticFieldRef byte[] SecP256k1/r;
		// 139
		virtualMethodRef 2.15.3(Ljavacard/security/Key;B)V;		// init(Ljavacard/security/Key;B)V
			.descriptor	Ljavacard/security/Key;	2.0;

		// 140
		virtualMethodRef 2.15.7([BSS[BSS)Z;		// verify([BSS[BSS)Z
		// 141
		staticMethodRef Tools/satoshisPlusLE([B[BS)V;
	}

	.class public AppletInstructions 0 extends 0.0 {		// extends java/lang/Object

		.fields {
			public static final short PACKET_BUFFER_SIZE = 250;		// S
			public static final short INSTRUCTION_VERSION = 0;		// S
			public static final short CLASS_PSBT_UPLOAD = 0;		// S
			public static final short CLASS_POLICY_UPLOAD = 1;		// S
			public static final short CLASS_HAND_SHAKE = 3;		// S
			public static final short CLASS_ADDITIONAL_DATA_UPLOAD = 2;		// S
			public static final short CLASS_DOWNLOAD_PSBT_ARRAY = 4;		// S
			public static final short CLASS_SET_MODE_SECRET = 14;		// S
			public static final short CLASS_SET_MODE_TIME = 15;		// S
			public static final short CLASS_DOWNLOAD_GLOBAL_MAP = 5;		// S
			public static final short INS_DOWNLOAD_NUM_INPUT_V0 = 5;		// S
			public static final short INS_DOWNLOAD_NUM_OUTPUT_V0 = 4;		// S
			public static final short INS_DOWNLOAD_VERSION = 6;		// S
			public static final short INS_DOWNLOAD_SIZE = 7;		// S
			public static final short CLASS_DOWNLOAD_INPUT_MAP = 6;		// S
			public static final short CLASS_DOWNLOAD_OUTPUT_MAP = 7;		// S
			public static final short CLASS_DOWNLOAD_INPUT = 12;		// S
			public static final short CLASS_DOWNLOAD_OUTPUT = 13;		// S
			public static final short CLASS_DOWNLOAD_GLOBAL_ALL = 8;		// S
			public static final short CLASS_DOWNLOAD_INPUT_ALL = 9;		// S
			public static final short CLASS_DOWNLOAD_OUTPUT_ALL = 10;		// S
			public static final short CLASS_DOWNLOAD_GLOBAL_MAP_KEYPAIR = 11;		// S
			public static final short CLASS_DOWNLOAD_POLICY_SIZE = 14;		// S
			public static final short CLASS_DOWNLOAD_POLICY = 15;		// S
			public static final short CLASS_VALIDATE_POLICY = 16;		// S
			public static final short INS_REQUEST = 0;		// S
			public static final short INS_UPLOAD = 1;		// S
			public static final short INS_FINISH = 2;		// S
			public static final short INS_DOWNLOAD_ARRAY = 3;		// S
			public static final byte PSBT_GLOBAL_UNSIGNED_TX = 0;		// B
			public static final byte PSBT_GLOBAL_XPUB = 1;		// B
			public static final byte PSBT_GLOBAL_TX_VERSION = 2;		// B
			public static final byte PSBT_GLOBAL_FALLBACK_LOCKTIME = 3;		// B
			public static final byte PSBT_GLOBAL_INPUT_COUNT = 4;		// B
			public static final byte PSBT_GLOBAL_OUTPUT_COUNT = 5;		// B
			public static final byte PSBT_GLOBAL_TX_MODIFIABLE = 6;		// B
			public static final byte PSBT_GLOBAL_SIGHASH_SINGLE_INPUTS = 7;		// B
			public static final byte PSBT_GLOBAL_VERSION = -5;		// B
			public static final byte PSBT_GLOBAL_PROPRIETARY = -4;		// B
			public static final byte PSBT_OUT_AMOUNT = 3;		// B
			public static final byte PSBT_OUT_SCRIPT = 4;		// B
		}

		.publicMethodTable 1 {
			equals(Ljava/lang/Object;)Z;
		}

		.packageMethodTable 0 {
		}

		.method public <init>()V 0 {
			.stack 1;
			.locals 0;

				L0:	aload_0;
					invokespecial 57;		// java/lang/Object.<init>()V
					return;
		}

	}

	.class public ArrayInDisguise 1 extends 0.0 {		// extends java/lang/Object

		.fields {
			public short offset 0;		// S
			public byte[] array 1;		// [B
		}

		.publicMethodTable 1 {
			equals(Ljava/lang/Object;)Z;
		}

		.packageMethodTable 0 {
		}

		.method  <init>(S)V {
			.stack 2;
			.locals 0;

				L0:	aload_0;
					invokespecial 57;		// java/lang/Object.<init>()V
					aload_0;
					sload_1;
					newarray 11;
					putfield_a 0;		// reference applet/ArrayInDisguise.array
					sconst_0;
					putfield_s_this 1;		// short applet/ArrayInDisguise.offset
					return;
		}

	}

	.class public FromApplet 2 extends 0.0 {		// extends java/lang/Object

		.publicMethodTable 1 {
			equals(Ljava/lang/Object;)Z;
		}

		.packageMethodTable 0 {
		}

		.method public <init>()V 0 {
			.stack 1;
			.locals 0;

				L0:	aload_0;
					invokespecial 57;		// java/lang/Object.<init>()V
					return;
		}

		.method static send_data(Ljavacard/framework/APDU;[BSS)V {
			.stack 6;
			.locals 0;

			.descriptor	Ljavacard/framework/APDU;	1.10;

				L0:	aload_1;
					sload_2;
					aload_0;
					invokevirtual 59;		// getBuffer()[B
					sconst_0;
					sload_3;
					sload_2;
					ssub;
					invokestatic 125;		// javacard/framework/Util.arrayCopyNonAtomic([BS[BSS)S
					pop;
					aload_0;
					sconst_0;
					sload_3;
					sload_2;
					ssub;
					invokevirtual 44;		// setOutgoingAndSend(SS)V
					return;
		}

		.method static send_data(Ljavacard/framework/APDU;S)V {
			.stack 4;
			.locals 0;

			.descriptor	Ljavacard/framework/APDU;	1.10;

				L0:	aload_0;
					invokevirtual 59;		// getBuffer()[B
					sconst_0;
					sload_1;
					bspush 8;
					sshl;
					s2b;
					bastore;
					aload_0;
					invokevirtual 59;		// getBuffer()[B
					sconst_1;
					sload_1;
					s2b;
					bastore;
					aload_0;
					sconst_0;
					sconst_4;
					invokevirtual 44;		// setOutgoingAndSend(SS)V
					return;
		}

		.method static send_data(Ljavacard/framework/APDU;Lapplet/GeneralMap;)V {
			.stack 4;
			.locals 0;

			.descriptor	Ljavacard/framework/APDU;	1.10;

				L0:	aload_0;
					invokevirtual 59;		// getBuffer()[B
					sconst_0;
					aload_1;
					getfield_s 2;		// short applet/GeneralMap.map_start
					bspush 8;
					sshl;
					s2b;
					bastore;
					aload_0;
					invokevirtual 59;		// getBuffer()[B
					sconst_1;
					aload_1;
					getfield_s 2;		// short applet/GeneralMap.map_start
					s2b;
					bastore;
					aload_0;
					invokevirtual 59;		// getBuffer()[B
					sconst_2;
					aload_1;
					getfield_s 2;		// short applet/GeneralMap.map_start
					aload_1;
					getfield_s 3;		// short applet/GeneralMap.map_size
					sadd;
					bspush 8;
					sshl;
					s2b;
					bastore;
					aload_0;
					invokevirtual 59;		// getBuffer()[B
					sconst_3;
					aload_1;
					getfield_s 2;		// short applet/GeneralMap.map_start
					aload_1;
					getfield_s 3;		// short applet/GeneralMap.map_size
					sadd;
					s2b;
					bastore;
					aload_0;
					sconst_0;
					sconst_4;
					invokevirtual 44;		// setOutgoingAndSend(SS)V
					return;
		}

		.method static send_data(Ljavacard/framework/APDU;Lapplet/PSBTKeyPair;)V {
			.stack 4;
			.locals 0;

			.descriptor	Ljavacard/framework/APDU;	1.10;

				L0:	aload_0;
					invokevirtual 59;		// getBuffer()[B
					sconst_0;
					aload_1;
					getfield_a 4;		// reference applet/PSBTKeyPair.key
					getfield_s 5;		// short applet/PSBTKey.start
					bspush 8;
					sshl;
					s2b;
					bastore;
					aload_0;
					invokevirtual 59;		// getBuffer()[B
					sconst_1;
					aload_1;
					getfield_a 4;		// reference applet/PSBTKeyPair.key
					getfield_s 5;		// short applet/PSBTKey.start
					s2b;
					bastore;
					aload_0;
					invokevirtual 59;		// getBuffer()[B
					sconst_2;
					aload_1;
					getfield_a 4;		// reference applet/PSBTKeyPair.key
					getfield_s 5;		// short applet/PSBTKey.start
					aload_1;
					invokevirtual 56;		// getSize()S
					sadd;
					bspush 8;
					sshl;
					s2b;
					bastore;
					aload_0;
					invokevirtual 59;		// getBuffer()[B
					sconst_3;
					aload_1;
					getfield_a 4;		// reference applet/PSBTKeyPair.key
					getfield_s 5;		// short applet/PSBTKey.start
					aload_1;
					invokevirtual 56;		// getSize()S
					sadd;
					s2b;
					bastore;
					aload_0;
					sconst_0;
					sconst_4;
					invokevirtual 44;		// setOutgoingAndSend(SS)V
					return;
		}

		.method public static send_data(Ljavacard/framework/APDU;Lapplet/GlobalUnsignedTXInput;)V 1 {
			.stack 4;
			.locals 0;

			.descriptor	Ljavacard/framework/APDU;	1.10;

				L0:	aload_0;
					invokevirtual 59;		// getBuffer()[B
					sconst_0;
					aload_1;
					getfield_s 6;		// short applet/GlobalUnsignedTXInput.previous_output_start
					bspush 8;
					sshl;
					s2b;
					bastore;
					aload_0;
					invokevirtual 59;		// getBuffer()[B
					sconst_1;
					aload_1;
					getfield_s 6;		// short applet/GlobalUnsignedTXInput.previous_output_start
					s2b;
					bastore;
					aload_0;
					invokevirtual 59;		// getBuffer()[B
					sconst_2;
					aload_1;
					getfield_s 7;		// short applet/GlobalUnsignedTXInput.size
					aload_1;
					getfield_s 6;		// short applet/GlobalUnsignedTXInput.previous_output_start
					sadd;
					bspush 8;
					sshl;
					s2b;
					bastore;
					aload_0;
					invokevirtual 59;		// getBuffer()[B
					sconst_3;
					aload_1;
					getfield_s 7;		// short applet/GlobalUnsignedTXInput.size
					aload_1;
					getfield_s 6;		// short applet/GlobalUnsignedTXInput.previous_output_start
					sadd;
					s2b;
					bastore;
					aload_0;
					sconst_0;
					sconst_4;
					invokevirtual 44;		// setOutgoingAndSend(SS)V
					return;
		}

		.method public static send_data(Ljavacard/framework/APDU;Lapplet/GlobalUnsignedTXOutput;)V 2 {
			.stack 4;
			.locals 0;

			.descriptor	Ljavacard/framework/APDU;	1.10;

				L0:	aload_0;
					invokevirtual 59;		// getBuffer()[B
					sconst_0;
					aload_1;
					getfield_s 8;		// short applet/GlobalUnsignedTXOutput.valueStart
					bspush 8;
					sshl;
					s2b;
					bastore;
					aload_0;
					invokevirtual 59;		// getBuffer()[B
					sconst_1;
					aload_1;
					getfield_s 8;		// short applet/GlobalUnsignedTXOutput.valueStart
					s2b;
					bastore;
					aload_0;
					invokevirtual 59;		// getBuffer()[B
					sconst_2;
					aload_1;
					getfield_s 9;		// short applet/GlobalUnsignedTXOutput.size
					aload_1;
					getfield_s 8;		// short applet/GlobalUnsignedTXOutput.valueStart
					sadd;
					bspush 8;
					sshl;
					s2b;
					bastore;
					aload_0;
					invokevirtual 59;		// getBuffer()[B
					sconst_3;
					aload_1;
					getfield_s 9;		// short applet/GlobalUnsignedTXOutput.size
					aload_1;
					getfield_s 8;		// short applet/GlobalUnsignedTXOutput.valueStart
					sadd;
					s2b;
					bastore;
					aload_0;
					sconst_0;
					sconst_4;
					invokevirtual 44;		// setOutgoingAndSend(SS)V
					return;
		}

	}

	.class public GeneralMap 3 extends 0.0 {		// extends java/lang/Object

		.fields {
			public short map_start 0;		// S
			public short NUM_OF_KEYPAIR 1;		// S
			public short currentKeyPair 2;		// S
			public short map_size 3;		// S
			public PSBTKeyPair[] keyPairs 4;		// [Lapplet/PSBTKeyPair;
		}

		.publicMethodTable 1 {
			equals(Ljava/lang/Object;)Z;
			fill(S)V;
			reset()V;
		}

		.packageMethodTable 0 {
		}

		.method public <init>()V 0 {
			.stack 4;
			.locals 1;

				L0:	aload_0;
					invokespecial 57;		// java/lang/Object.<init>()V
					sconst_m1;
					putfield_s_this 2;		// short applet/GeneralMap.map_start
					bspush 8;
					putfield_s_this 10;		// short applet/GeneralMap.NUM_OF_KEYPAIR
					sconst_m1;
					putfield_s_this 11;		// short applet/GeneralMap.currentKeyPair
					aload_0;
					getfield_s_this 10;		// short applet/GeneralMap.NUM_OF_KEYPAIR
					anewarray 58;		// applet/PSBTKeyPair
					putfield_a 12;		// reference applet/GeneralMap.keyPairs
					sconst_0;
					putfield_s_this 3;		// short applet/GeneralMap.map_size
					sconst_0;
					sstore_1;
				L1:	sload_1;
					getfield_s_this 10;		// short applet/GeneralMap.NUM_OF_KEYPAIR
					if_scmpge L3;
				L2:	getfield_a_this 12;		// reference applet/GeneralMap.keyPairs
					sload_1;
					new 58;		// applet/PSBTKeyPair
					dup;
					invokespecial 94;		// applet/PSBTKeyPair.<init>()V
					aastore;
					sinc 1 1;
					goto L1;
				L3:	return;
		}

		.method public fill(S)V 1 {
			.stack 4;
			.locals 0;

				L0:	aload_0;
					sload_1;
					sconst_1;
					sadd;
					putfield_s 2;		// short applet/GeneralMap.map_start
				L1:	getstatic_a 95;		// reference applet/MainApplet.PSBTdata
					sload_1;
					getfield_s_this 3;		// short applet/GeneralMap.map_size
					sadd;
					baload;
					sspush 255;
					sand;
					ifeq L4;
				L2:	getfield_s_this 11;		// short applet/GeneralMap.currentKeyPair
					getfield_s_this 10;		// short applet/GeneralMap.NUM_OF_KEYPAIR
					sconst_1;
					ssub;
					if_scmpge L4;
				L3:	aload_0;
					dup;
					getfield_s 11;		// short applet/GeneralMap.currentKeyPair
					sconst_1;
					sadd;
					putfield_s 11;		// short applet/GeneralMap.currentKeyPair
					getfield_a_this 12;		// reference applet/GeneralMap.keyPairs
					getfield_s_this 11;		// short applet/GeneralMap.currentKeyPair
					aaload;
					sload_1;
					getfield_s_this 3;		// short applet/GeneralMap.map_size
					sadd;
					invokevirtual 107;		// fill(S)V
					aload_0;
					dup;
					getfield_s 3;		// short applet/GeneralMap.map_size
					getfield_a_this 12;		// reference applet/GeneralMap.keyPairs
					getfield_s_this 11;		// short applet/GeneralMap.currentKeyPair
					aaload;
					invokevirtual 56;		// getSize()S
					sadd;
					putfield_s 3;		// short applet/GeneralMap.map_size
					goto L1;
				L4:	return;
		}

		.method public reset()V 2 {
			.stack 2;
			.locals 1;

				L0:	sconst_0;
					sstore_1;
				L1:	sload_1;
					getfield_s_this 10;		// short applet/GeneralMap.NUM_OF_KEYPAIR
					if_scmpge L3;
				L2:	getfield_a_this 12;		// reference applet/GeneralMap.keyPairs
					sload_1;
					aaload;
					invokevirtual 112;		// reset()V
					sinc 1 1;
					goto L1;
				L3:	sconst_m1;
					putfield_s_this 2;		// short applet/GeneralMap.map_start
					sconst_m1;
					putfield_s_this 11;		// short applet/GeneralMap.currentKeyPair
					sconst_0;
					putfield_s_this 3;		// short applet/GeneralMap.map_size
					return;
		}

	}

	.class public GlobalMap 4 extends GeneralMap {

		.fields {
			 GlobalUnsignedTX globalUnsignedTX 0;		// Lapplet/GlobalUnsignedTX;
			 short input_maps_total 1;		// S
			 short outputMapsTotal 2;		// S
			static short PSBTversion;		// S
		}

		.publicMethodTable 1 {
			equals(Ljava/lang/Object;)Z;
			fill(S)V;
			reset()V;
		}

		.packageMethodTable 0 {
		}

		.method public <init>()V 0 {
			.stack 3;
			.locals 0;

				L0:	aload_0;
					invokespecial 114;		// applet/GeneralMap.<init>()V
					sconst_m1;
					putfield_s_this 13;		// short applet/GlobalMap.input_maps_total
					sconst_m1;
					putfield_s_this 14;		// short applet/GlobalMap.outputMapsTotal
					aload_0;
					new 45;		// applet/GlobalUnsignedTX
					dup;
					invokespecial 55;		// applet/GlobalUnsignedTX.<init>()V
					putfield_a 15;		// reference applet/GlobalMap.globalUnsignedTX
					return;
		}

		.method public fill(S)V 1 {
			.stack 4;
			.locals 0;

				L0:	aload_0;
					sload_1;
					sconst_1;
					sadd;
					putfield_s 2;		// short applet/GeneralMap.map_start
				L1:	getstatic_a 95;		// reference applet/MainApplet.PSBTdata
					sload_1;
					getfield_s_this 3;		// short applet/GeneralMap.map_size
					sadd;
					baload;
					sspush 255;
					sand;
					ifeq_w L12;
				L2:	getfield_s_this 11;		// short applet/GeneralMap.currentKeyPair
					getfield_s_this 10;		// short applet/GeneralMap.NUM_OF_KEYPAIR
					sconst_1;
					ssub;
					if_scmpge_w L12;
				L3:	aload_0;
					dup;
					getfield_s 11;		// short applet/GeneralMap.currentKeyPair
					sconst_1;
					sadd;
					putfield_s 11;		// short applet/GeneralMap.currentKeyPair
					getfield_a_this 12;		// reference applet/GeneralMap.keyPairs
					getfield_s_this 11;		// short applet/GeneralMap.currentKeyPair
					aaload;
					sload_1;
					getfield_s_this 3;		// short applet/GeneralMap.map_size
					sadd;
					invokevirtual 107;		// fill(S)V
					getfield_a_this 12;		// reference applet/GeneralMap.keyPairs
					getfield_s_this 11;		// short applet/GeneralMap.currentKeyPair
					aaload;
					getfield_a 4;		// reference applet/PSBTKeyPair.key
					getfield_s 16;		// short applet/PSBTKey.keyKype
					ifne L5;
				L4:	getfield_a_this 15;		// reference applet/GlobalMap.globalUnsignedTX
					sload_1;
					getfield_s_this 3;		// short applet/GeneralMap.map_size
					sadd;
					sconst_2;
					sadd;
					getfield_a_this 12;		// reference applet/GeneralMap.keyPairs
					getfield_s_this 11;		// short applet/GeneralMap.currentKeyPair
					aaload;
					getfield_a 17;		// reference applet/PSBTKeyPair.value
					getfield_s 18;		// short applet/PSBTValue.value_len_bytes
					sadd;
					invokevirtual 60;		// fill(S)V
				L5:	getfield_a_this 12;		// reference applet/GeneralMap.keyPairs
					getfield_s_this 11;		// short applet/GeneralMap.currentKeyPair
					aaload;
					getfield_a 4;		// reference applet/PSBTKeyPair.key
					getfield_s 16;		// short applet/PSBTKey.keyKype
					sconst_4;
					if_scmpne L7;
				L6:	aload_0;
					getfield_a_this 12;		// reference applet/GeneralMap.keyPairs
					getfield_s_this 11;		// short applet/GeneralMap.currentKeyPair
					aaload;
					getfield_a 17;		// reference applet/PSBTKeyPair.value
					sconst_0;
					invokevirtual 61;		// getByte(S)B
					putfield_s 13;		// short applet/GlobalMap.input_maps_total
				L7:	getfield_a_this 12;		// reference applet/GeneralMap.keyPairs
					getfield_s_this 11;		// short applet/GeneralMap.currentKeyPair
					aaload;
					getfield_a 4;		// reference applet/PSBTKeyPair.key
					getfield_s 16;		// short applet/PSBTKey.keyKype
					sconst_5;
					if_scmpne L9;
				L8:	aload_0;
					getfield_a_this 12;		// reference applet/GeneralMap.keyPairs
					getfield_s_this 11;		// short applet/GeneralMap.currentKeyPair
					aaload;
					getfield_a 17;		// reference applet/PSBTKeyPair.value
					sconst_0;
					invokevirtual 61;		// getByte(S)B
					putfield_s 14;		// short applet/GlobalMap.outputMapsTotal
				L9:	getfield_a_this 12;		// reference applet/GeneralMap.keyPairs
					getfield_s_this 11;		// short applet/GeneralMap.currentKeyPair
					aaload;
					getfield_a 4;		// reference applet/PSBTKeyPair.key
					getfield_s 16;		// short applet/PSBTKey.keyKype
					sconst_2;
					if_scmpne L11;
				L10:	getfield_a_this 12;		// reference applet/GeneralMap.keyPairs
					getfield_s_this 11;		// short applet/GeneralMap.currentKeyPair
					aaload;
					getfield_a 17;		// reference applet/PSBTKeyPair.value
					sconst_0;
					invokevirtual 61;		// getByte(S)B
					putstatic_s 86;		// short applet/GlobalMap.PSBTversion
				L11:	aload_0;
					dup;
					getfield_s 3;		// short applet/GeneralMap.map_size
					getfield_a_this 12;		// reference applet/GeneralMap.keyPairs
					getfield_s_this 11;		// short applet/GeneralMap.currentKeyPair
					aaload;
					invokevirtual 56;		// getSize()S
					sadd;
					putfield_s 3;		// short applet/GeneralMap.map_size
					goto_w L1;
				L12:	return;
		}

		.method public reset()V 2 {
			.stack 2;
			.locals 1;

				L0:	sconst_0;
					sstore_1;
				L1:	sload_1;
					getfield_s_this 10;		// short applet/GeneralMap.NUM_OF_KEYPAIR
					if_scmpge L3;
				L2:	getfield_a_this 12;		// reference applet/GeneralMap.keyPairs
					sload_1;
					aaload;
					invokevirtual 112;		// reset()V
					sinc 1 1;
					goto L1;
				L3:	sconst_m1;
					putfield_s_this 13;		// short applet/GlobalMap.input_maps_total
					sconst_m1;
					putfield_s_this 14;		// short applet/GlobalMap.outputMapsTotal
					sconst_0;
					putstatic_s 86;		// short applet/GlobalMap.PSBTversion
					getfield_a_this 15;		// reference applet/GlobalMap.globalUnsignedTX
					invokevirtual 91;		// reset()V
					sconst_m1;
					putfield_s_this 2;		// short applet/GeneralMap.map_start
					sconst_m1;
					putfield_s_this 11;		// short applet/GeneralMap.currentKeyPair
					sconst_0;
					putfield_s_this 3;		// short applet/GeneralMap.map_size
					return;
		}

	}

	.class public GlobalUnsignedTX 5 extends 0.0 {		// extends java/lang/Object

		.fields {
			 GlobalUnsignedTXInput[] inputs 0;		// [Lapplet/GlobalUnsignedTXInput;
			 GlobalUnsignedTXOutput[] outputs 1;		// [Lapplet/GlobalUnsignedTXOutput;
			 short start 2;		// S
			 short version 3;		// S
			 short size 4;		// S
			 short input_count 5;		// S
			 short output_count 6;		// S
			 short lockTimeStart 7;		// S
			static final short MAX_COUNT_OF_IO = 8;		// S
		}

		.publicMethodTable 1 {
			equals(Ljava/lang/Object;)Z;
			fill(S)V;
		}

		.packageMethodTable 0 {
			getCount()S;
			ignoreInput(S)S;
			reset()V;
		}

		.method  <init>()V {
			.stack 4;
			.locals 1;

				L0:	aload_0;
					invokespecial 57;		// java/lang/Object.<init>()V
					sconst_m1;
					putfield_s_this 19;		// short applet/GlobalUnsignedTX.start
					sconst_m1;
					putfield_s_this 20;		// short applet/GlobalUnsignedTX.version
					sconst_0;
					putfield_s_this 21;		// short applet/GlobalUnsignedTX.size
					sconst_m1;
					putfield_s_this 22;		// short applet/GlobalUnsignedTX.input_count
					aload_0;
					bspush 8;
					anewarray 113;		// applet/GlobalUnsignedTXInput
					putfield_a 23;		// reference applet/GlobalUnsignedTX.inputs
					sconst_m1;
					putfield_s_this 24;		// short applet/GlobalUnsignedTX.output_count
					aload_0;
					bspush 8;
					anewarray 126;		// applet/GlobalUnsignedTXOutput
					putfield_a 25;		// reference applet/GlobalUnsignedTX.outputs
					sconst_m1;
					putfield_s_this 26;		// short applet/GlobalUnsignedTX.lockTimeStart
					sconst_0;
					sstore_1;
				L1:	sload_1;
					bspush 8;
					if_scmpge L3;
				L2:	getfield_a_this 23;		// reference applet/GlobalUnsignedTX.inputs
					sload_1;
					new 113;		// applet/GlobalUnsignedTXInput
					dup;
					invokespecial 46;		// applet/GlobalUnsignedTXInput.<init>()V
					aastore;
					getfield_a_this 25;		// reference applet/GlobalUnsignedTX.outputs
					sload_1;
					new 126;		// applet/GlobalUnsignedTXOutput
					dup;
					invokespecial 47;		// applet/GlobalUnsignedTXOutput.<init>()V
					aastore;
					sinc 1 1;
					goto L1;
				L3:	return;
		}

		.method public fill(S)V 1 {
			.stack 4;
			.locals 1;

				L0:	sload_1;
					putfield_s_this 19;		// short applet/GlobalUnsignedTX.start
					aload_0;
					getstatic_a 95;		// reference applet/MainApplet.PSBTdata
					getfield_s_this 19;		// short applet/GlobalUnsignedTX.start
					baload;
					putfield_s 20;		// short applet/GlobalUnsignedTX.version
					aload_0;
					dup;
					getfield_s 21;		// short applet/GlobalUnsignedTX.size
					sconst_4;
					sadd;
					putfield_s 21;		// short applet/GlobalUnsignedTX.size
					aload_0;
					aload_0;
					invokevirtual 48;		// getCount()S
					putfield_s 22;		// short applet/GlobalUnsignedTX.input_count
					aload_0;
					dup;
					getfield_s 21;		// short applet/GlobalUnsignedTX.size
					getfield_s_this 22;		// short applet/GlobalUnsignedTX.input_count
					invokestatic 49;		// applet/Tools.byteSizeOfCWI(S)S
					sadd;
					putfield_s 21;		// short applet/GlobalUnsignedTX.size
					sconst_0;
					sstore_2;
				L1:	sload_2;
					getfield_s_this 22;		// short applet/GlobalUnsignedTX.input_count
					if_scmpge L3;
				L2:	getfield_a_this 23;		// reference applet/GlobalUnsignedTX.inputs
					sload_2;
					aaload;
					getfield_s_this 19;		// short applet/GlobalUnsignedTX.start
					getfield_s_this 21;		// short applet/GlobalUnsignedTX.size
					sadd;
					invokevirtual 50;		// fill(S)V
					aload_0;
					dup;
					getfield_s 21;		// short applet/GlobalUnsignedTX.size
					getfield_a_this 23;		// reference applet/GlobalUnsignedTX.inputs
					sload_2;
					aaload;
					getfield_s 7;		// short applet/GlobalUnsignedTXInput.size
					sadd;
					putfield_s 21;		// short applet/GlobalUnsignedTX.size
					sinc 2 1;
					goto L1;
				L3:	aload_0;
					aload_0;
					invokevirtual 48;		// getCount()S
					putfield_s 24;		// short applet/GlobalUnsignedTX.output_count
					aload_0;
					dup;
					getfield_s 21;		// short applet/GlobalUnsignedTX.size
					getfield_s_this 24;		// short applet/GlobalUnsignedTX.output_count
					invokestatic 49;		// applet/Tools.byteSizeOfCWI(S)S
					sadd;
					putfield_s 21;		// short applet/GlobalUnsignedTX.size
					sconst_0;
					sstore_2;
				L4:	sload_2;
					getfield_s_this 24;		// short applet/GlobalUnsignedTX.output_count
					if_scmpge L6;
				L5:	getfield_a_this 25;		// reference applet/GlobalUnsignedTX.outputs
					sload_2;
					aaload;
					getfield_s_this 19;		// short applet/GlobalUnsignedTX.start
					getfield_s_this 21;		// short applet/GlobalUnsignedTX.size
					sadd;
					invokevirtual 51;		// fill(S)V
					aload_0;
					dup;
					getfield_s 21;		// short applet/GlobalUnsignedTX.size
					getfield_a_this 25;		// reference applet/GlobalUnsignedTX.outputs
					sload_2;
					aaload;
					getfield_s 9;		// short applet/GlobalUnsignedTXOutput.size
					sadd;
					putfield_s 21;		// short applet/GlobalUnsignedTX.size
					sinc 2 1;
					goto L4;
				L6:	aload_0;
					getfield_s_this 21;		// short applet/GlobalUnsignedTX.size
					putfield_s 26;		// short applet/GlobalUnsignedTX.lockTimeStart
					aload_0;
					dup;
					getfield_s 21;		// short applet/GlobalUnsignedTX.size
					sconst_4;
					sadd;
					putfield_s 21;		// short applet/GlobalUnsignedTX.size
					return;
		}

		.method  getCount()S 128 {
			.stack 2;
			.locals 0;

				L0:	getfield_s_this 19;		// short applet/GlobalUnsignedTX.start
					getfield_s_this 21;		// short applet/GlobalUnsignedTX.size
					sadd;
					invokestatic 52;		// applet/Tools.compactWeirdoInt(S)S
					sreturn;
		}

		.method  ignoreInput(S)S 129 {
			.stack 2;
			.locals 1;

				L0:	sload_1;
					bspush 36;
					sadd;
					invokestatic 52;		// applet/Tools.compactWeirdoInt(S)S
					sstore_2;
					sload_2;
					bspush 40;
					sadd;
					sload_2;
					invokestatic 49;		// applet/Tools.byteSizeOfCWI(S)S
					sadd;
					sreturn;
		}

		.method  reset()V 130 {
			.stack 2;
			.locals 1;

				L0:	sconst_0;
					sstore_1;
				L1:	sload_1;
					bspush 8;
					if_scmpge L3;
				L2:	getfield_a_this 23;		// reference applet/GlobalUnsignedTX.inputs
					sload_1;
					aaload;
					invokevirtual 53;		// reset()V
					getfield_a_this 25;		// reference applet/GlobalUnsignedTX.outputs
					sload_1;
					aaload;
					invokevirtual 54;		// reset()V
					sinc 1 1;
					goto L1;
				L3:	sconst_m1;
					putfield_s_this 19;		// short applet/GlobalUnsignedTX.start
					sconst_m1;
					putfield_s_this 20;		// short applet/GlobalUnsignedTX.version
					sconst_0;
					putfield_s_this 21;		// short applet/GlobalUnsignedTX.size
					return;
		}

	}

	.class public GlobalUnsignedTXInput 6 extends 0.0 {		// extends java/lang/Object

		.fields {
			 short previous_output_start 0;		// S
			 short script_size_start 1;		// S
			 short script_size 2;		// S
			 short script_sig_start 3;		// S
			 short sequence_start 4;		// S
			 short size 5;		// S
		}

		.publicMethodTable 1 {
			equals(Ljava/lang/Object;)Z;
		}

		.packageMethodTable 0 {
			fill(S)V;
			reset()V;
		}

		.method public <init>()V 0 {
			.stack 2;
			.locals 0;

				L0:	aload_0;
					invokespecial 57;		// java/lang/Object.<init>()V
					sconst_m1;
					putfield_s_this 6;		// short applet/GlobalUnsignedTXInput.previous_output_start
					sconst_m1;
					putfield_s_this 27;		// short applet/GlobalUnsignedTXInput.script_size_start
					sconst_m1;
					putfield_s_this 28;		// short applet/GlobalUnsignedTXInput.script_size
					sconst_m1;
					putfield_s_this 29;		// short applet/GlobalUnsignedTXInput.script_sig_start
					sconst_m1;
					putfield_s_this 30;		// short applet/GlobalUnsignedTXInput.sequence_start
					sconst_0;
					putfield_s_this 7;		// short applet/GlobalUnsignedTXInput.size
					return;
		}

		.method  fill(S)V 128 {
			.stack 3;
			.locals 0;

				L0:	sload_1;
					putfield_s_this 6;		// short applet/GlobalUnsignedTXInput.previous_output_start
					aload_0;
					sload_1;
					bspush 36;
					sadd;
					putfield_s 27;		// short applet/GlobalUnsignedTXInput.script_size_start
					aload_0;
					getfield_s_this 27;		// short applet/GlobalUnsignedTXInput.script_size_start
					invokestatic 52;		// applet/Tools.compactWeirdoInt(S)S
					putfield_s 28;		// short applet/GlobalUnsignedTXInput.script_size
					aload_0;
					getfield_s_this 27;		// short applet/GlobalUnsignedTXInput.script_size_start
					getfield_s_this 28;		// short applet/GlobalUnsignedTXInput.script_size
					invokestatic 49;		// applet/Tools.byteSizeOfCWI(S)S
					sadd;
					putfield_s 29;		// short applet/GlobalUnsignedTXInput.script_sig_start
					aload_0;
					getfield_s_this 29;		// short applet/GlobalUnsignedTXInput.script_sig_start
					getfield_s_this 28;		// short applet/GlobalUnsignedTXInput.script_size
					sadd;
					putfield_s 30;		// short applet/GlobalUnsignedTXInput.sequence_start
					aload_0;
					bspush 36;
					getfield_s_this 28;		// short applet/GlobalUnsignedTXInput.script_size
					invokestatic 49;		// applet/Tools.byteSizeOfCWI(S)S
					sadd;
					getfield_s_this 28;		// short applet/GlobalUnsignedTXInput.script_size
					sadd;
					sconst_4;
					sadd;
					putfield_s 7;		// short applet/GlobalUnsignedTXInput.size
					return;
		}

		.method  reset()V 129 {
			.stack 2;
			.locals 0;

				L0:	sconst_m1;
					putfield_s_this 6;		// short applet/GlobalUnsignedTXInput.previous_output_start
					sconst_m1;
					putfield_s_this 27;		// short applet/GlobalUnsignedTXInput.script_size_start
					sconst_m1;
					putfield_s_this 28;		// short applet/GlobalUnsignedTXInput.script_size
					sconst_m1;
					putfield_s_this 29;		// short applet/GlobalUnsignedTXInput.script_sig_start
					sconst_m1;
					putfield_s_this 30;		// short applet/GlobalUnsignedTXInput.sequence_start
					sconst_0;
					putfield_s_this 7;		// short applet/GlobalUnsignedTXInput.size
					return;
		}

	}

	.class public GlobalUnsignedTXOutput 7 extends 0.0 {		// extends java/lang/Object

		.fields {
			 short valueStart 0;		// S
			 short script_size_start 1;		// S
			 short script_size 2;		// S
			 short script_pub_key_start 3;		// S
			 short size 4;		// S
		}

		.publicMethodTable 1 {
			equals(Ljava/lang/Object;)Z;
		}

		.packageMethodTable 0 {
			fill(S)V;
			reset()V;
		}

		.method public <init>()V 0 {
			.stack 2;
			.locals 0;

				L0:	aload_0;
					invokespecial 57;		// java/lang/Object.<init>()V
					sconst_m1;
					putfield_s_this 8;		// short applet/GlobalUnsignedTXOutput.valueStart
					sconst_m1;
					putfield_s_this 31;		// short applet/GlobalUnsignedTXOutput.script_size_start
					sconst_m1;
					putfield_s_this 32;		// short applet/GlobalUnsignedTXOutput.script_size
					sconst_m1;
					putfield_s_this 33;		// short applet/GlobalUnsignedTXOutput.script_pub_key_start
					sconst_0;
					putfield_s_this 9;		// short applet/GlobalUnsignedTXOutput.size
					return;
		}

		.method  fill(S)V 128 {
			.stack 3;
			.locals 0;

				L0:	sload_1;
					putfield_s_this 8;		// short applet/GlobalUnsignedTXOutput.valueStart
					aload_0;
					sload_1;
					bspush 8;
					sadd;
					putfield_s 31;		// short applet/GlobalUnsignedTXOutput.script_size_start
					aload_0;
					getfield_s_this 31;		// short applet/GlobalUnsignedTXOutput.script_size_start
					invokestatic 52;		// applet/Tools.compactWeirdoInt(S)S
					putfield_s 32;		// short applet/GlobalUnsignedTXOutput.script_size
					aload_0;
					getfield_s_this 31;		// short applet/GlobalUnsignedTXOutput.script_size_start
					getfield_s_this 32;		// short applet/GlobalUnsignedTXOutput.script_size
					invokestatic 49;		// applet/Tools.byteSizeOfCWI(S)S
					sadd;
					putfield_s 33;		// short applet/GlobalUnsignedTXOutput.script_pub_key_start
					aload_0;
					bspush 8;
					getfield_s_this 32;		// short applet/GlobalUnsignedTXOutput.script_size
					invokestatic 49;		// applet/Tools.byteSizeOfCWI(S)S
					sadd;
					getfield_s_this 32;		// short applet/GlobalUnsignedTXOutput.script_size
					sadd;
					putfield_s 9;		// short applet/GlobalUnsignedTXOutput.size
					return;
		}

		.method  reset()V 129 {
			.stack 2;
			.locals 0;

				L0:	sconst_m1;
					putfield_s_this 8;		// short applet/GlobalUnsignedTXOutput.valueStart
					sconst_m1;
					putfield_s_this 31;		// short applet/GlobalUnsignedTXOutput.script_size_start
					sconst_m1;
					putfield_s_this 32;		// short applet/GlobalUnsignedTXOutput.script_size
					sconst_m1;
					putfield_s_this 33;		// short applet/GlobalUnsignedTXOutput.script_pub_key_start
					sconst_0;
					putfield_s_this 9;		// short applet/GlobalUnsignedTXOutput.size
					return;
		}

	}

	.class public MainApplet 8 extends 1.3 {		// extends javacard/framework/Applet

		.fields {
			public static final short MAX_SIZE_OF_PSBT = 6144;		// S
			public static final short MAX_SIZE_OF_POLICY = 256;		// S
			public static final short STORAGE_AMOUNT = 16;		// S
			public static final short STORAGE_SIZE = 128;		// S
			public static PSBT psbt 0;		// Lapplet/PSBT;
			public static ArrayInDisguise[] privDataStorage 1;		// [Lapplet/ArrayInDisguise;
			public static ArrayInDisguise[] pubDataStorage 2;		// [Lapplet/ArrayInDisguise;
			public static byte[] PSBTdata 3;		// [B
			public static byte[] policy 4;		// [B
			public static byte[] totalOutput 5;		// [B
			static short transactionOffset;		// S
			static short policyOffset;		// S
			static short policyUploadLocked;		// S
		}

		.publicMethodTable 7 {
			equals(Ljava/lang/Object;)Z;
			register()V;
			register([BSB)V;
			selectingApplet()Z;
			deselect()V;
			getShareableInterfaceObject(Ljavacard/framework/AID;B)Ljavacard/framework/Shareable;;
			select()Z;
			process(Ljavacard/framework/APDU;)V;
			select(Z)Z;
			deselect(Z)V;
		}

		.packageMethodTable 0 {
			validatePolicy()S;
			checkStorageUsage()Z;
		}

		.implementedInterfaceInfoTable { 
			.interface 1.17 { 		// javacard/framework/MultiSelectable
				8;		// select(Z)Z
				9;		// deselect(Z)V
			}

		}

		.method public static install([BSB)V 0 {
			.stack 5;
			.locals 0;

				L0:	new 62;		// applet/MainApplet
					dup;
					aload_0;
					sload_1;
					sload_2;
					invokespecial 63;		// applet/MainApplet.<init>([BSB)V
					pop;
					return;
		}

		.method public <init>([BSB)V 1 {
			.stack 5;
			.locals 1;

				L0:	aload_0;
					invokespecial 64;		// javacard/framework/Applet.<init>()V
					new 65;		// applet/PSBT
					dup;
					invokespecial 66;		// applet/PSBT.<init>()V
					putstatic_a 67;		// reference applet/MainApplet.psbt
					bspush 16;
					anewarray 68;		// applet/ArrayInDisguise
					putstatic_a 69;		// reference applet/MainApplet.privDataStorage
					bspush 16;
					anewarray 68;		// applet/ArrayInDisguise
					putstatic_a 70;		// reference applet/MainApplet.pubDataStorage
					sconst_0;
					sstore 4;
				L1:	sload 4;
					bspush 16;
					if_scmpge L3;
				L2:	getstatic_a 69;		// reference applet/MainApplet.privDataStorage
					sload 4;
					new 68;		// applet/ArrayInDisguise
					dup;
					sspush 128;
					invokespecial 71;		// applet/ArrayInDisguise.<init>(S)V
					aastore;
					getstatic_a 70;		// reference applet/MainApplet.pubDataStorage
					sload 4;
					new 68;		// applet/ArrayInDisguise
					dup;
					sspush 128;
					invokespecial 71;		// applet/ArrayInDisguise.<init>(S)V
					aastore;
					sinc 4 1;
					goto L1;
				L3:	sspush 6144;
					newarray 11;
					putstatic_a 95;		// reference applet/MainApplet.PSBTdata
					sspush 256;
					newarray 11;
					putstatic_a 72;		// reference applet/MainApplet.policy
					bspush 8;
					newarray 11;
					putstatic_a 73;		// reference applet/MainApplet.totalOutput
					sconst_0;
					putstatic_s 74;		// short applet/MainApplet.transactionOffset
					sconst_0;
					putstatic_s 75;		// short applet/MainApplet.policyOffset
					sconst_0;
					putstatic_s 76;		// short applet/MainApplet.policyUploadLocked
					aload_0;
					invokevirtual 77;		// register()V
					return;
		}

		.method public process(Ljavacard/framework/APDU;)V 7 {
			.stack 6;
			.locals 9;

			.descriptor	Ljavacard/framework/APDU;	1.10;

				L0:	aload_1;
					invokevirtual 59;		// getBuffer()[B
					astore_2;
					aload_2;
					sconst_0;
					baload;
					sstore_3;
					aload_2;
					sconst_1;
					baload;
					sstore 4;
					aload_2;
					sconst_4;
					baload;
					sstore 5;
					aload_2;
					sconst_2;
					baload;
					sstore 6;
					aload_2;
					sconst_3;
					baload;
					sstore 7;
					aload_2;
					sconst_5;
					baload;
					sstore 8;
					sload_3;
					ifne L9;
				L1:	sload 4;
					ifne L3;
				L2:	sconst_0;
					putstatic_s 74;		// short applet/MainApplet.transactionOffset
				L3:	sload 4;
					sconst_1;
					if_scmpne L5;
				L4:	aload_2;
					sconst_5;
					getstatic_a 95;		// reference applet/MainApplet.PSBTdata
					getstatic_s 74;		// short applet/MainApplet.transactionOffset
					sload 5;
					sspush 255;
					sand;
					invokestatic 125;		// javacard/framework/Util.arrayCopyNonAtomic([BS[BSS)S
					pop;
					getstatic_s 74;		// short applet/MainApplet.transactionOffset
					sload 5;
					sspush 255;
					sand;
					sadd;
					putstatic_s 74;		// short applet/MainApplet.transactionOffset
				L5:	sload 4;
					sconst_2;
					if_scmpne L9;
				L6:	getstatic_a 67;		// reference applet/MainApplet.psbt
					invokevirtual 79;		// reset()V
					getstatic_a 67;		// reference applet/MainApplet.psbt
					invokevirtual 80;		// fill()V
				L7:	goto L9;
				L8:	astore 9;
					sspush -31949;
					invokestatic 81;		// javacard/framework/ISOException.throwIt(S)V
				L9:	sload_3;
					sconst_1;
					if_scmpne L12;
				L10:	getstatic_s 76;		// short applet/MainApplet.policyUploadLocked
					sconst_1;
					if_scmpne L12;
				L11:	sspush -31676;
					invokestatic 81;		// javacard/framework/ISOException.throwIt(S)V
				L12:	sload_3;
					sconst_1;
					if_scmpne L21;
				L13:	getstatic_s 76;		// short applet/MainApplet.policyUploadLocked
					ifne L21;
				L14:	sload 4;
					ifne L15;
				L15:	sload 4;
					sconst_1;
					if_scmpne L17;
				L16:	aload_2;
					sconst_5;
					getstatic_a 72;		// reference applet/MainApplet.policy
					getstatic_s 75;		// short applet/MainApplet.policyOffset
					sload 5;
					sspush 255;
					sand;
					invokestatic 125;		// javacard/framework/Util.arrayCopyNonAtomic([BS[BSS)S
					pop;
					getstatic_s 75;		// short applet/MainApplet.policyOffset
					sload 5;
					sspush 255;
					sand;
					sadd;
					putstatic_s 75;		// short applet/MainApplet.policyOffset
				L17:	sload 4;
					sconst_2;
					if_scmpne L21;
				L18:	aload_0;
					invokevirtual 82;		// checkStorageUsage()Z
					ifne L20;
				L19:	sspush -31130;
					invokestatic 81;		// javacard/framework/ISOException.throwIt(S)V
				L20:	sconst_1;
					putstatic_s 76;		// short applet/MainApplet.policyUploadLocked
				L21:	sload_3;
					sconst_2;
					if_scmpne L28;
				L22:	getstatic_s 76;		// short applet/MainApplet.policyUploadLocked
					ifne L28;
				L23:	sload 4;
					ifne L25;
				L24:	getstatic_a 69;		// reference applet/MainApplet.privDataStorage
					sload 6;
					aaload;
					sconst_0;
					putfield_s 1;		// short applet/ArrayInDisguise.offset
				L25:	sload 4;
					sconst_1;
					if_scmpne L27;
				L26:	aload_2;
					sconst_5;
					getstatic_a 69;		// reference applet/MainApplet.privDataStorage
					sload 6;
					aaload;
					getfield_a 0;		// reference applet/ArrayInDisguise.array
					getstatic_a 69;		// reference applet/MainApplet.privDataStorage
					sload 6;
					aaload;
					getfield_s 1;		// short applet/ArrayInDisguise.offset
					sload 5;
					sspush 255;
					sand;
					invokestatic 125;		// javacard/framework/Util.arrayCopyNonAtomic([BS[BSS)S
					pop;
					getstatic_a 69;		// reference applet/MainApplet.privDataStorage
					sload 6;
					aaload;
					dup;
					getfield_s 1;		// short applet/ArrayInDisguise.offset
					sload 5;
					sspush 255;
					sand;
					sadd;
					putfield_s 1;		// short applet/ArrayInDisguise.offset
				L27:	sload 4;
					sconst_2;
					if_scmpne L28;
				L28:	sload_3;
					sconst_2;
					if_scmpne L35;
				L29:	getstatic_s 76;		// short applet/MainApplet.policyUploadLocked
					sconst_1;
					if_scmpne L35;
				L30:	sload 4;
					ifne L32;
				L31:	getstatic_a 70;		// reference applet/MainApplet.pubDataStorage
					sload 6;
					aaload;
					sconst_0;
					putfield_s 1;		// short applet/ArrayInDisguise.offset
				L32:	sload 4;
					sconst_1;
					if_scmpne L34;
				L33:	aload_2;
					sconst_5;
					getstatic_a 70;		// reference applet/MainApplet.pubDataStorage
					sload 6;
					aaload;
					getfield_a 0;		// reference applet/ArrayInDisguise.array
					getstatic_a 70;		// reference applet/MainApplet.pubDataStorage
					sload 6;
					aaload;
					getfield_s 1;		// short applet/ArrayInDisguise.offset
					sload 5;
					sspush 255;
					sand;
					invokestatic 125;		// javacard/framework/Util.arrayCopyNonAtomic([BS[BSS)S
					pop;
					getstatic_a 70;		// reference applet/MainApplet.pubDataStorage
					sload 6;
					aaload;
					dup;
					getfield_s 1;		// short applet/ArrayInDisguise.offset
					sload 5;
					sspush 255;
					sand;
					sadd;
					putfield_s 1;		// short applet/ArrayInDisguise.offset
				L34:	sload 4;
					sconst_2;
					if_scmpne L35;
				L35:	sload_3;
					sconst_4;
					if_scmpne L41;
				L36:	sload 4;
					sconst_3;
					if_scmpne L41;
				L37:	aload_2;
					sconst_5;
					baload;
					sspush 255;
					sand;
					bspush 8;
					sshl;
					aload_2;
					bspush 6;
					baload;
					sspush 255;
					sand;
					sor;
					sstore 9;
					aload_2;
					bspush 7;
					baload;
					sspush 255;
					sand;
					bspush 8;
					sshl;
					aload_2;
					bspush 8;
					baload;
					sspush 255;
					sand;
					sor;
					sstore 10;
					sload 9;
					iflt L39;
				L38:	sload 10;
					getstatic_a 95;		// reference applet/MainApplet.PSBTdata
					arraylength;
					if_scmple L40;
				L39:	return;
				L40:	aload_1;
					getstatic_a 95;		// reference applet/MainApplet.PSBTdata
					sload 9;
					sload 10;
					invokestatic 83;		// applet/FromApplet.send_data(Ljavacard/framework/APDU;[BSS)V
				L41:	sload_3;
					sconst_5;
					if_scmpne L44;
				L42:	sload 4;
					bspush 6;
					if_scmpne L44;
				L43:	aload_1;
					getstatic_s 86;		// short applet/GlobalMap.PSBTversion
					invokestatic 84;		// applet/FromApplet.send_data(Ljavacard/framework/APDU;S)V
				L44:	sload_3;
					sconst_5;
					if_scmpne L47;
				L45:	sload 4;
					bspush 7;
					if_scmpne L47;
				L46:	aload_1;
					getstatic_s 85;		// short applet/PSBT.byte_size
					invokestatic 84;		// applet/FromApplet.send_data(Ljavacard/framework/APDU;S)V
				L47:	sload_3;
					sconst_5;
					if_scmpne L53;
				L48:	sload 4;
					sconst_5;
					if_scmpne L53;
				L49:	getstatic_s 86;		// short applet/GlobalMap.PSBTversion
					ifne L51;
				L50:	aload_1;
					getstatic_a 67;		// reference applet/MainApplet.psbt
					getfield_a 34;		// reference applet/PSBT.globalMap
					getfield_a 15;		// reference applet/GlobalMap.globalUnsignedTX
					getfield_s 22;		// short applet/GlobalUnsignedTX.input_count
					invokestatic 84;		// applet/FromApplet.send_data(Ljavacard/framework/APDU;S)V
				L51:	getstatic_s 86;		// short applet/GlobalMap.PSBTversion
					sconst_2;
					if_scmpne L53;
				L52:	aload_1;
					getstatic_s 87;		// short applet/PSBT.current_input_map
					invokestatic 84;		// applet/FromApplet.send_data(Ljavacard/framework/APDU;S)V
				L53:	sload_3;
					sconst_5;
					if_scmpne L59;
				L54:	sload 4;
					sconst_4;
					if_scmpne L59;
				L55:	getstatic_s 86;		// short applet/GlobalMap.PSBTversion
					ifne L57;
				L56:	aload_1;
					getstatic_a 67;		// reference applet/MainApplet.psbt
					getfield_a 34;		// reference applet/PSBT.globalMap
					getfield_a 15;		// reference applet/GlobalMap.globalUnsignedTX
					getfield_s 24;		// short applet/GlobalUnsignedTX.output_count
					invokestatic 84;		// applet/FromApplet.send_data(Ljavacard/framework/APDU;S)V
				L57:	getstatic_s 86;		// short applet/GlobalMap.PSBTversion
					sconst_2;
					if_scmpne L59;
				L58:	aload_1;
					getstatic_s 88;		// short applet/PSBT.current_output_map
					invokestatic 84;		// applet/FromApplet.send_data(Ljavacard/framework/APDU;S)V
				L59:	sload_3;
					bspush 14;
					if_scmpne L62;
				L60:	sload 4;
					ifne L62;
				L61:	aload_1;
					getstatic_s 75;		// short applet/MainApplet.policyOffset
					invokestatic 84;		// applet/FromApplet.send_data(Ljavacard/framework/APDU;S)V
				L62:	sload_3;
					bspush 15;
					if_scmpne L64;
				L63:	aload_2;
					sconst_5;
					baload;
					sspush 255;
					sand;
					bspush 8;
					sshl;
					aload_2;
					bspush 6;
					baload;
					sspush 255;
					sand;
					sor;
					sstore 9;
					aload_2;
					bspush 7;
					baload;
					sspush 255;
					sand;
					bspush 8;
					sshl;
					aload_2;
					bspush 8;
					baload;
					sspush 255;
					sand;
					sor;
					sstore 10;
					aload_1;
					getstatic_a 72;		// reference applet/MainApplet.policy
					sload 9;
					sload 10;
					invokestatic 83;		// applet/FromApplet.send_data(Ljavacard/framework/APDU;[BSS)V
				L64:	sload_3;
					bspush 16;
					if_scmpne L66;
				L65:	aload_1;
					aload_0;
					invokevirtual 89;		// validatePolicy()S
					invokestatic 84;		// applet/FromApplet.send_data(Ljavacard/framework/APDU;S)V
				L66:	sload_3;
					bspush 12;
					if_scmpne L71;
				L67:	getstatic_s 86;		// short applet/GlobalMap.PSBTversion
					ifne L69;
				L68:	aload_1;
					getstatic_a 67;		// reference applet/MainApplet.psbt
					getfield_a 34;		// reference applet/PSBT.globalMap
					getfield_a 15;		// reference applet/GlobalMap.globalUnsignedTX
					getfield_a 23;		// reference applet/GlobalUnsignedTX.inputs
					sload 6;
					aaload;
					invokestatic 90;		// applet/FromApplet.send_data(Ljavacard/framework/APDU;Lapplet/GlobalUnsignedTXInput;)V
				L69:	getstatic_s 86;		// short applet/GlobalMap.PSBTversion
					sconst_2;
					if_scmpne L71;
				L70:	aload_1;
					getstatic_a 67;		// reference applet/MainApplet.psbt
					getfield_a 35;		// reference applet/PSBT.input_maps
					sload 6;
					aaload;
					invokestatic 92;		// applet/FromApplet.send_data(Ljavacard/framework/APDU;Lapplet/GeneralMap;)V
				L71:	sload_3;
					bspush 13;
					if_scmpne L76;
				L72:	getstatic_s 86;		// short applet/GlobalMap.PSBTversion
					ifne L74;
				L73:	aload_1;
					getstatic_a 67;		// reference applet/MainApplet.psbt
					getfield_a 34;		// reference applet/PSBT.globalMap
					getfield_a 15;		// reference applet/GlobalMap.globalUnsignedTX
					getfield_a 25;		// reference applet/GlobalUnsignedTX.outputs
					sload 6;
					aaload;
					invokestatic 93;		// applet/FromApplet.send_data(Ljavacard/framework/APDU;Lapplet/GlobalUnsignedTXOutput;)V
				L74:	getstatic_s 86;		// short applet/GlobalMap.PSBTversion
					sconst_2;
					if_scmpne L76;
				L75:	aload_1;
					getstatic_a 67;		// reference applet/MainApplet.psbt
					getfield_a 36;		// reference applet/PSBT.outputMaps
					sload 6;
					aaload;
					invokestatic 92;		// applet/FromApplet.send_data(Ljavacard/framework/APDU;Lapplet/GeneralMap;)V
				L76:	sload_3;
					bspush 8;
					if_scmpne L78;
				L77:	aload_1;
					getstatic_a 67;		// reference applet/MainApplet.psbt
					getfield_a 34;		// reference applet/PSBT.globalMap
					invokestatic 92;		// applet/FromApplet.send_data(Ljavacard/framework/APDU;Lapplet/GeneralMap;)V
				L78:	sload_3;
					bspush 9;
					if_scmpne L80;
				L79:	aload_1;
					getstatic_a 67;		// reference applet/MainApplet.psbt
					getfield_a 35;		// reference applet/PSBT.input_maps
					sload 6;
					aaload;
					invokestatic 92;		// applet/FromApplet.send_data(Ljavacard/framework/APDU;Lapplet/GeneralMap;)V
				L80:	sload_3;
					bspush 10;
					if_scmpne L82;
				L81:	aload_1;
					getstatic_a 67;		// reference applet/MainApplet.psbt
					getfield_a 36;		// reference applet/PSBT.outputMaps
					sload 6;
					aaload;
					invokestatic 92;		// applet/FromApplet.send_data(Ljavacard/framework/APDU;Lapplet/GeneralMap;)V
				L82:	sload_3;
					bspush 11;
					if_scmpne L84;
				L83:	aload_1;
					getstatic_a 67;		// reference applet/MainApplet.psbt
					getfield_a 34;		// reference applet/PSBT.globalMap
					getfield_a 37;		// reference applet/GeneralMap.keyPairs
					sload 6;
					aaload;
					invokestatic 96;		// applet/FromApplet.send_data(Ljavacard/framework/APDU;Lapplet/PSBTKeyPair;)V
				L84:	sload_3;
					sconst_3;
					if_scmpne L86;
				L85:	bspush 10;
					newarray 11;
					dup;
					sconst_0;
					bspush 72;
					bastore;
					dup;
					sconst_1;
					bspush 65;
					bastore;
					dup;
					sconst_2;
					bspush 78;
					bastore;
					dup;
					sconst_3;
					bspush 68;
					bastore;
					dup;
					sconst_4;
					bspush 32;
					bastore;
					dup;
					sconst_5;
					bspush 83;
					bastore;
					dup;
					bspush 6;
					bspush 72;
					bastore;
					dup;
					bspush 7;
					bspush 65;
					bastore;
					dup;
					bspush 8;
					bspush 75;
					bastore;
					dup;
					bspush 9;
					bspush 69;
					bastore;
					astore 9;
					aload 9;
					sconst_0;
					aload_2;
					sconst_0;
					aload 9;
					arraylength;
					invokestatic 125;		// javacard/framework/Util.arrayCopyNonAtomic([BS[BSS)S
					pop;
					aload_1;
					sconst_0;
					aload 9;
					arraylength;
					invokevirtual 44;		// setOutgoingAndSend(SS)V
				L86:	return;
			.exceptionTable {
				// start_block end_block handler_block catch_type_index
				L6 L7 L8 78;
			}
		}

		.method  validatePolicy()S 128 {
			.stack 8;
			.locals 3;

				L0:	sconst_0;
					sstore_1;
					sconst_0;
					sstore_2;
					getstatic_s 75;		// short applet/MainApplet.policyOffset
					ifne L2;
				L1:	sconst_1;
					sreturn;
				L2:	sload_1;
					getstatic_s 75;		// short applet/MainApplet.policyOffset
					if_scmpge_w L63;
				L3:	getstatic_a 72;		// reference applet/MainApplet.policy
					sload_1;
					baload;
					stableswitch L62 0 13 L4 L7 L10 L13 L16 L23 L30 L37 L44 L49 L53 L62 L56 L59;
				L4:	getstatic_a 72;		// reference applet/MainApplet.policy
					sload_1;
					sconst_1;
					sadd;
					baload;
					sconst_1;
					invokestatic 97;		// applet/Policy.validateTotalOutput(BS)Z
					ifeq L6;
				L5:	sconst_1;
					sstore_2;
				L6:	sinc 1 2;
					goto L2;
				L7:	getstatic_a 72;		// reference applet/MainApplet.policy
					sload_1;
					sconst_1;
					sadd;
					baload;
					sconst_m1;
					invokestatic 97;		// applet/Policy.validateTotalOutput(BS)Z
					ifeq L9;
				L8:	sconst_1;
					sstore_2;
				L9:	sinc 1 2;
					goto L2;
				L10:	getstatic_a 72;		// reference applet/MainApplet.policy
					sload_1;
					sconst_1;
					sadd;
					baload;
					getstatic_a 72;		// reference applet/MainApplet.policy
					sload_1;
					sconst_2;
					sadd;
					baload;
					sconst_1;
					invokestatic 98;		// applet/Policy.validateValueOwSS(BBS)Z
					ifeq L12;
				L11:	sconst_1;
					sstore_2;
				L12:	sinc 1 3;
					goto L2;
				L13:	getstatic_a 72;		// reference applet/MainApplet.policy
					sload_1;
					sconst_1;
					sadd;
					baload;
					getstatic_a 72;		// reference applet/MainApplet.policy
					sload_1;
					sconst_2;
					sadd;
					baload;
					sconst_m1;
					invokestatic 98;		// applet/Policy.validateValueOwSS(BBS)Z
					ifeq L15;
				L14:	sconst_1;
					sstore_2;
				L15:	sinc 1 3;
					goto_w L2;
				L16:	getstatic_s 86;		// short applet/GlobalMap.PSBTversion
					ifne L19;
				L17:	getstatic_a 72;		// reference applet/MainApplet.policy
					sload_1;
					sconst_1;
					sadd;
					baload;
					getstatic_a 67;		// reference applet/MainApplet.psbt
					getfield_a 34;		// reference applet/PSBT.globalMap
					getfield_a 15;		// reference applet/GlobalMap.globalUnsignedTX
					getfield_s 22;		// short applet/GlobalUnsignedTX.input_count
					if_scmpgt L19;
				L18:	sconst_1;
					sstore_2;
				L19:	getstatic_s 86;		// short applet/GlobalMap.PSBTversion
					sconst_2;
					if_scmpne L22;
				L20:	getstatic_a 72;		// reference applet/MainApplet.policy
					sload_1;
					sconst_1;
					sadd;
					baload;
					getstatic_a 67;		// reference applet/MainApplet.psbt
					getfield_a 34;		// reference applet/PSBT.globalMap
					getfield_s 13;		// short applet/GlobalMap.input_maps_total
					if_scmpgt L22;
				L21:	sconst_1;
					sstore_2;
				L22:	sinc 1 2;
					goto_w L2;
				L23:	getstatic_s 86;		// short applet/GlobalMap.PSBTversion
					ifne L26;
				L24:	getstatic_a 72;		// reference applet/MainApplet.policy
					sload_1;
					sconst_1;
					sadd;
					baload;
					getstatic_a 67;		// reference applet/MainApplet.psbt
					getfield_a 34;		// reference applet/PSBT.globalMap
					getfield_a 15;		// reference applet/GlobalMap.globalUnsignedTX
					getfield_s 22;		// short applet/GlobalUnsignedTX.input_count
					if_scmplt L26;
				L25:	sconst_1;
					sstore_2;
				L26:	getstatic_s 86;		// short applet/GlobalMap.PSBTversion
					sconst_2;
					if_scmpne L29;
				L27:	getstatic_a 72;		// reference applet/MainApplet.policy
					sload_1;
					sconst_1;
					sadd;
					baload;
					getstatic_a 67;		// reference applet/MainApplet.psbt
					getfield_a 34;		// reference applet/PSBT.globalMap
					getfield_s 13;		// short applet/GlobalMap.input_maps_total
					if_scmplt L29;
				L28:	sconst_1;
					sstore_2;
				L29:	sinc 1 2;
					goto_w L2;
				L30:	getstatic_s 86;		// short applet/GlobalMap.PSBTversion
					ifne L33;
				L31:	getstatic_a 72;		// reference applet/MainApplet.policy
					sload_1;
					sconst_1;
					sadd;
					baload;
					getstatic_a 67;		// reference applet/MainApplet.psbt
					getfield_a 34;		// reference applet/PSBT.globalMap
					getfield_a 15;		// reference applet/GlobalMap.globalUnsignedTX
					getfield_s 24;		// short applet/GlobalUnsignedTX.output_count
					if_scmpgt L33;
				L32:	sconst_1;
					sstore_2;
				L33:	getstatic_s 86;		// short applet/GlobalMap.PSBTversion
					sconst_2;
					if_scmpne L36;
				L34:	getstatic_a 72;		// reference applet/MainApplet.policy
					sload_1;
					sconst_1;
					sadd;
					baload;
					getstatic_a 67;		// reference applet/MainApplet.psbt
					getfield_a 34;		// reference applet/PSBT.globalMap
					getfield_s 14;		// short applet/GlobalMap.outputMapsTotal
					if_scmpgt L36;
				L35:	sconst_1;
					sstore_2;
				L36:	sinc 1 2;
					goto_w L2;
				L37:	getstatic_s 86;		// short applet/GlobalMap.PSBTversion
					ifne L40;
				L38:	getstatic_a 72;		// reference applet/MainApplet.policy
					sload_1;
					sconst_1;
					sadd;
					baload;
					getstatic_a 67;		// reference applet/MainApplet.psbt
					getfield_a 34;		// reference applet/PSBT.globalMap
					getfield_a 15;		// reference applet/GlobalMap.globalUnsignedTX
					getfield_s 24;		// short applet/GlobalUnsignedTX.output_count
					if_scmplt L40;
				L39:	sconst_1;
					sstore_2;
				L40:	getstatic_s 86;		// short applet/GlobalMap.PSBTversion
					sconst_2;
					if_scmpne L43;
				L41:	getstatic_a 72;		// reference applet/MainApplet.policy
					sload_1;
					sconst_1;
					sadd;
					baload;
					getstatic_a 67;		// reference applet/MainApplet.psbt
					getfield_a 34;		// reference applet/PSBT.globalMap
					getfield_s 14;		// short applet/GlobalMap.outputMapsTotal
					if_scmplt L43;
				L42:	sconst_1;
					sstore_2;
				L43:	sinc 1 2;
					goto_w L2;
				L44:	getstatic_a 95;		// reference applet/MainApplet.PSBTdata
					getstatic_s 74;		// short applet/MainApplet.transactionOffset
					getstatic_a 70;		// reference applet/MainApplet.pubDataStorage
					getstatic_a 72;		// reference applet/MainApplet.policy
					sload_1;
					sconst_1;
					sadd;
					baload;
					aaload;
					getfield_a 0;		// reference applet/ArrayInDisguise.array
					getstatic_a 70;		// reference applet/MainApplet.pubDataStorage
					getstatic_a 72;		// reference applet/MainApplet.policy
					sload_1;
					sconst_1;
					sadd;
					baload;
					aaload;
					getfield_s 1;		// short applet/ArrayInDisguise.offset
					invokestatic 99;		// applet/SetAndVerify.verifyECDSA([BS[BS)Z
					ifeq L46;
				L45:	sconst_1;
					sstore_2;
				L46:	goto L48;
				L47:	astore_3;
					sspush -27580;
					invokestatic 81;		// javacard/framework/ISOException.throwIt(S)V
				L48:	sinc 1 2;
					goto_w L2;
				L49:	getstatic_a 69;		// reference applet/MainApplet.privDataStorage
					getstatic_a 72;		// reference applet/MainApplet.policy
					sload_1;
					sconst_1;
					sadd;
					baload;
					aaload;
					getfield_a 0;		// reference applet/ArrayInDisguise.array
					getstatic_a 69;		// reference applet/MainApplet.privDataStorage
					getstatic_a 72;		// reference applet/MainApplet.policy
					sload_1;
					sconst_1;
					sadd;
					baload;
					aaload;
					getfield_s 1;		// short applet/ArrayInDisguise.offset
					invokestatic 100;		// applet/SetAndVerify.setPublicKey([BS)V
					getstatic_a 70;		// reference applet/MainApplet.pubDataStorage
					getstatic_a 72;		// reference applet/MainApplet.policy
					sload_1;
					sconst_2;
					sadd;
					baload;
					aaload;
					getfield_a 0;		// reference applet/ArrayInDisguise.array
					getstatic_a 70;		// reference applet/MainApplet.pubDataStorage
					getstatic_a 72;		// reference applet/MainApplet.policy
					sload_1;
					sconst_2;
					sadd;
					baload;
					aaload;
					getfield_s 1;		// short applet/ArrayInDisguise.offset
					getstatic_a 70;		// reference applet/MainApplet.pubDataStorage
					getstatic_a 72;		// reference applet/MainApplet.policy
					sload_1;
					sconst_1;
					sadd;
					baload;
					aaload;
					getfield_a 0;		// reference applet/ArrayInDisguise.array
					getstatic_a 70;		// reference applet/MainApplet.pubDataStorage
					getstatic_a 72;		// reference applet/MainApplet.policy
					sload_1;
					sconst_1;
					sadd;
					baload;
					aaload;
					getfield_s 1;		// short applet/ArrayInDisguise.offset
					invokestatic 99;		// applet/SetAndVerify.verifyECDSA([BS[BS)Z
					ifeq L52;
				L50:	getstatic_a 70;		// reference applet/MainApplet.pubDataStorage
					getstatic_a 72;		// reference applet/MainApplet.policy
					sload_1;
					sconst_2;
					sadd;
					baload;
					aaload;
					getfield_a 0;		// reference applet/ArrayInDisguise.array
					sconst_0;
					getstatic_a 69;		// reference applet/MainApplet.privDataStorage
					getstatic_a 72;		// reference applet/MainApplet.policy
					sload_1;
					sconst_2;
					sadd;
					baload;
					aaload;
					getfield_a 0;		// reference applet/ArrayInDisguise.array
					sconst_0;
					getstatic_a 69;		// reference applet/MainApplet.privDataStorage
					getstatic_a 72;		// reference applet/MainApplet.policy
					sload_1;
					sconst_2;
					sadd;
					baload;
					aaload;
					getfield_s 1;		// short applet/ArrayInDisguise.offset
					invokestatic 101;		// javacard/framework/Util.arrayCompare([BS[BSS)B
					sconst_m1;
					if_scmpeq L52;
				L51:	sconst_1;
					sstore_2;
				L52:	sinc 1 3;
					goto_w L2;
				L53:	getstatic_a 69;		// reference applet/MainApplet.privDataStorage
					getstatic_a 72;		// reference applet/MainApplet.policy
					sload_1;
					sconst_1;
					sadd;
					baload;
					aaload;
					getfield_a 0;		// reference applet/ArrayInDisguise.array
					sconst_0;
					getstatic_a 70;		// reference applet/MainApplet.pubDataStorage
					getstatic_a 72;		// reference applet/MainApplet.policy
					sload_1;
					sconst_1;
					sadd;
					baload;
					aaload;
					getfield_a 0;		// reference applet/ArrayInDisguise.array
					sconst_0;
					sspush 128;
					invokestatic 101;		// javacard/framework/Util.arrayCompare([BS[BSS)B
					ifne L55;
				L54:	sconst_1;
					sstore_2;
				L55:	sinc 1 2;
					goto_w L2;
				L56:	getstatic_a 72;		// reference applet/MainApplet.policy
					sload_1;
					sconst_1;
					sadd;
					baload;
					getstatic_s 86;		// short applet/GlobalMap.PSBTversion
					if_scmpne L58;
				L57:	sconst_1;
					sstore_2;
				L58:	sinc 1 2;
					goto_w L2;
				L59:	sload_2;
					ifne L61;
				L60:	aload_0;
					sconst_0;
					invokespecial 102;		// applet/MainApplet.validationReturnProcedure(S)S
					sreturn;
				L61:	sconst_0;
					sstore_2;
					sinc 1 1;
					goto_w L2;
				L62:	aload_0;
					sconst_0;
					invokespecial 102;		// applet/MainApplet.validationReturnProcedure(S)S
					sreturn;
				L63:	aload_0;
					sload_2;
					invokespecial 102;		// applet/MainApplet.validationReturnProcedure(S)S
					sreturn;
			.exceptionTable {
				// start_block end_block handler_block catch_type_index
				L44 L46 L47 78;
			}
		}

		.method  checkStorageUsage()Z 129 {
			.stack 4;
			.locals 1;

				L0:	sconst_0;
					sstore_1;
				L1:	sload_1;
					getstatic_s 75;		// short applet/MainApplet.policyOffset
					if_scmpge_w L34;
				L2:	getstatic_a 72;		// reference applet/MainApplet.policy
					sload_1;
					baload;
					stableswitch L33 0 13 L3 L6 L9 L13 L17 L18 L19 L20 L21 L24 L28 L33 L31 L32;
				L3:	getstatic_a 69;		// reference applet/MainApplet.privDataStorage
					getstatic_a 72;		// reference applet/MainApplet.policy
					sload_1;
					sconst_1;
					sadd;
					baload;
					aaload;
					getfield_s 1;		// short applet/ArrayInDisguise.offset
					ifne L5;
				L4:	sconst_0;
					sreturn;
				L5:	sinc 1 2;
					goto L1;
				L6:	getstatic_a 69;		// reference applet/MainApplet.privDataStorage
					getstatic_a 72;		// reference applet/MainApplet.policy
					sload_1;
					sconst_1;
					sadd;
					baload;
					aaload;
					getfield_s 1;		// short applet/ArrayInDisguise.offset
					ifne L8;
				L7:	sconst_0;
					sreturn;
				L8:	sinc 1 2;
					goto L1;
				L9:	getstatic_a 69;		// reference applet/MainApplet.privDataStorage
					getstatic_a 72;		// reference applet/MainApplet.policy
					sload_1;
					sconst_1;
					sadd;
					baload;
					aaload;
					getfield_s 1;		// short applet/ArrayInDisguise.offset
					ifeq L11;
				L10:	getstatic_a 69;		// reference applet/MainApplet.privDataStorage
					getstatic_a 72;		// reference applet/MainApplet.policy
					sload_1;
					sconst_2;
					sadd;
					baload;
					aaload;
					getfield_s 1;		// short applet/ArrayInDisguise.offset
					ifne L12;
				L11:	sconst_0;
					sreturn;
				L12:	sinc 1 3;
					goto L1;
				L13:	getstatic_a 69;		// reference applet/MainApplet.privDataStorage
					getstatic_a 72;		// reference applet/MainApplet.policy
					sload_1;
					sconst_1;
					sadd;
					baload;
					aaload;
					getfield_s 1;		// short applet/ArrayInDisguise.offset
					ifeq L15;
				L14:	getstatic_a 69;		// reference applet/MainApplet.privDataStorage
					getstatic_a 72;		// reference applet/MainApplet.policy
					sload_1;
					sconst_2;
					sadd;
					baload;
					aaload;
					getfield_s 1;		// short applet/ArrayInDisguise.offset
					ifne L16;
				L15:	sconst_0;
					sreturn;
				L16:	sinc 1 3;
					goto_w L1;
				L17:	sinc 1 2;
					goto_w L1;
				L18:	sinc 1 2;
					goto_w L1;
				L19:	sinc 1 2;
					goto_w L1;
				L20:	sinc 1 2;
					goto_w L1;
				L21:	getstatic_a 69;		// reference applet/MainApplet.privDataStorage
					getstatic_a 72;		// reference applet/MainApplet.policy
					sload_1;
					sconst_1;
					sadd;
					baload;
					aaload;
					getfield_s 1;		// short applet/ArrayInDisguise.offset
					ifne L23;
				L22:	sconst_0;
					sreturn;
				L23:	sinc 1 2;
					goto_w L1;
				L24:	getstatic_a 69;		// reference applet/MainApplet.privDataStorage
					getstatic_a 72;		// reference applet/MainApplet.policy
					sload_1;
					sconst_1;
					sadd;
					baload;
					aaload;
					getfield_s 1;		// short applet/ArrayInDisguise.offset
					ifeq L26;
				L25:	getstatic_a 69;		// reference applet/MainApplet.privDataStorage
					getstatic_a 72;		// reference applet/MainApplet.policy
					sload_1;
					sconst_2;
					sadd;
					baload;
					aaload;
					getfield_s 1;		// short applet/ArrayInDisguise.offset
					ifne L27;
				L26:	sconst_0;
					sreturn;
				L27:	sinc 1 3;
					goto_w L1;
				L28:	getstatic_a 69;		// reference applet/MainApplet.privDataStorage
					getstatic_a 72;		// reference applet/MainApplet.policy
					sload_1;
					sconst_1;
					sadd;
					baload;
					aaload;
					getfield_s 1;		// short applet/ArrayInDisguise.offset
					ifne L30;
				L29:	sconst_0;
					sreturn;
				L30:	sinc 1 2;
					goto_w L1;
				L31:	sinc 1 2;
					goto_w L1;
				L32:	sinc 1 1;
					goto_w L1;
				L33:	goto_w L1;
				L34:	sconst_1;
					sreturn;
		}

		.method private validationReturnProcedure(S)S {
			.stack 3;
			.locals 2;

				L0:	sconst_0;
					sstore_2;
					sconst_0;
					sstore_3;
				L1:	sload_2;
					bspush 16;
					if_scmpge L5;
				L2:	sload_3;
					sspush 128;
					if_scmpge L4;
				L3:	getstatic_a 70;		// reference applet/MainApplet.pubDataStorage
					sload_2;
					aaload;
					getfield_a 0;		// reference applet/ArrayInDisguise.array
					sload_3;
					sconst_0;
					bastore;
					sinc 3 1;
					goto L2;
				L4:	getstatic_a 70;		// reference applet/MainApplet.pubDataStorage
					sload_2;
					aaload;
					sconst_0;
					putfield_s 1;		// short applet/ArrayInDisguise.offset
					sconst_0;
					sstore_3;
					sinc 2 1;
					goto L1;
				L5:	sload_1;
					sreturn;
		}

		.method public select(Z)Z 8 {
			.stack 1;
			.locals 0;

				L0:	sconst_1;
					sreturn;
		}

		.method public deselect(Z)V 9 {
			.stack 0;
			.locals 0;

				L0:	return;
		}

	}

	.class public PSBT 9 extends 0.0 {		// extends java/lang/Object

		.fields {
			public GlobalMap globalMap 0;		// Lapplet/GlobalMap;
			public GeneralMap[] input_maps 1;		// [Lapplet/GeneralMap;
			public GeneralMap[] outputMaps 2;		// [Lapplet/GeneralMap;
			public static final short MAX_OF_IO_MAPS = 8;		// S
			public static short current_input_map 0;		// S
			public static short current_output_map 1;		// S
			static short byte_size;		// S
		}

		.publicMethodTable 1 {
			equals(Ljava/lang/Object;)Z;
			fill()V;
			reset()V;
		}

		.packageMethodTable 0 {
		}

		.method public <init>()V 0 {
			.stack 4;
			.locals 1;

				L0:	aload_0;
					invokespecial 57;		// java/lang/Object.<init>()V
					aload_0;
					new 103;		// applet/GlobalMap
					dup;
					invokespecial 104;		// applet/GlobalMap.<init>()V
					putfield_a 34;		// reference applet/PSBT.globalMap
					aload_0;
					bspush 8;
					anewarray 105;		// applet/GeneralMap
					putfield_a 35;		// reference applet/PSBT.input_maps
					aload_0;
					bspush 8;
					anewarray 105;		// applet/GeneralMap
					putfield_a 36;		// reference applet/PSBT.outputMaps
					sconst_0;
					sstore_1;
				L1:	sload_1;
					bspush 8;
					if_scmpge L3;
				L2:	getfield_a_this 35;		// reference applet/PSBT.input_maps
					sload_1;
					new 105;		// applet/GeneralMap
					dup;
					invokespecial 114;		// applet/GeneralMap.<init>()V
					aastore;
					getfield_a_this 36;		// reference applet/PSBT.outputMaps
					sload_1;
					new 105;		// applet/GeneralMap
					dup;
					invokespecial 114;		// applet/GeneralMap.<init>()V
					aastore;
					sinc 1 1;
					goto L1;
				L3:	return;
		}

		.method public fill()V 1 {
			.stack 3;
			.locals 0;

				L0:	getstatic_a 95;		// reference applet/MainApplet.PSBTdata
					sconst_0;
					baload;
					sspush 255;
					sand;
					bspush 112;
					if_scmpne L5;
				L1:	getstatic_a 95;		// reference applet/MainApplet.PSBTdata
					sconst_1;
					baload;
					sspush 255;
					sand;
					bspush 115;
					if_scmpne L5;
				L2:	getstatic_a 95;		// reference applet/MainApplet.PSBTdata
					sconst_2;
					baload;
					sspush 255;
					sand;
					bspush 98;
					if_scmpne L5;
				L3:	getstatic_a 95;		// reference applet/MainApplet.PSBTdata
					sconst_3;
					baload;
					sspush 255;
					sand;
					bspush 116;
					if_scmpne L5;
				L4:	getstatic_a 95;		// reference applet/MainApplet.PSBTdata
					sconst_4;
					baload;
					sspush 255;
					sand;
					sspush 255;
					if_scmpeq L6;
				L5:	return;
				L6:	getstatic_s 85;		// short applet/PSBT.byte_size
					sconst_5;
					sadd;
					putstatic_s 85;		// short applet/PSBT.byte_size
					getfield_a_this 34;		// reference applet/PSBT.globalMap
					sconst_5;
					invokevirtual 106;		// fill(S)V
					getstatic_s 85;		// short applet/PSBT.byte_size
					getfield_a_this 34;		// reference applet/PSBT.globalMap
					getfield_s 38;		// short applet/GeneralMap.map_size
					sadd;
					putstatic_s 85;		// short applet/PSBT.byte_size
					getstatic_s 85;		// short applet/PSBT.byte_size
					sconst_1;
					sadd;
					putstatic_s 85;		// short applet/PSBT.byte_size
				L7:	getstatic_s 87;		// short applet/PSBT.current_input_map
					getfield_a_this 34;		// reference applet/PSBT.globalMap
					getfield_s 13;		// short applet/GlobalMap.input_maps_total
					if_scmpge L9;
				L8:	getfield_a_this 35;		// reference applet/PSBT.input_maps
					getstatic_s 87;		// short applet/PSBT.current_input_map
					aaload;
					getstatic_s 85;		// short applet/PSBT.byte_size
					invokevirtual 108;		// fill(S)V
					getstatic_s 85;		// short applet/PSBT.byte_size
					getfield_a_this 35;		// reference applet/PSBT.input_maps
					getstatic_s 87;		// short applet/PSBT.current_input_map
					aaload;
					getfield_s 3;		// short applet/GeneralMap.map_size
					sadd;
					putstatic_s 85;		// short applet/PSBT.byte_size
					getstatic_s 85;		// short applet/PSBT.byte_size
					sconst_1;
					sadd;
					putstatic_s 85;		// short applet/PSBT.byte_size
					getstatic_s 87;		// short applet/PSBT.current_input_map
					sconst_1;
					sadd;
					putstatic_s 87;		// short applet/PSBT.current_input_map
					goto L7;
				L9:	getstatic_s 88;		// short applet/PSBT.current_output_map
					getfield_a_this 34;		// reference applet/PSBT.globalMap
					getfield_s 14;		// short applet/GlobalMap.outputMapsTotal
					if_scmpge L11;
				L10:	getfield_a_this 36;		// reference applet/PSBT.outputMaps
					getstatic_s 88;		// short applet/PSBT.current_output_map
					aaload;
					getstatic_s 85;		// short applet/PSBT.byte_size
					invokevirtual 108;		// fill(S)V
					getstatic_s 85;		// short applet/PSBT.byte_size
					getfield_a_this 36;		// reference applet/PSBT.outputMaps
					getstatic_s 88;		// short applet/PSBT.current_output_map
					aaload;
					getfield_s 3;		// short applet/GeneralMap.map_size
					sadd;
					putstatic_s 85;		// short applet/PSBT.byte_size
					getstatic_s 85;		// short applet/PSBT.byte_size
					sconst_1;
					sadd;
					putstatic_s 85;		// short applet/PSBT.byte_size
					getstatic_s 88;		// short applet/PSBT.current_output_map
					sconst_1;
					sadd;
					putstatic_s 88;		// short applet/PSBT.current_output_map
					goto L9;
				L11:	invokestatic 109;		// applet/Tools.getTotalOutput()V
					return;
		}

		.method public reset()V 2 {
			.stack 3;
			.locals 1;

				L0:	sconst_0;
					sstore_1;
					getfield_a_this 34;		// reference applet/PSBT.globalMap
					invokevirtual 110;		// reset()V
				L1:	sload_1;
					bspush 8;
					if_scmpge L3;
				L2:	getfield_a_this 35;		// reference applet/PSBT.input_maps
					sload_1;
					aaload;
					invokevirtual 111;		// reset()V
					getfield_a_this 36;		// reference applet/PSBT.outputMaps
					sload_1;
					aaload;
					invokevirtual 111;		// reset()V
					sinc 1 1;
					goto L1;
				L3:	sconst_0;
					sstore_1;
				L4:	sload_1;
					bspush 8;
					if_scmpge L6;
				L5:	getstatic_a 73;		// reference applet/MainApplet.totalOutput
					sload_1;
					sconst_0;
					bastore;
					sinc 1 1;
					goto L4;
				L6:	sconst_0;
					putstatic_s 87;		// short applet/PSBT.current_input_map
					sconst_0;
					putstatic_s 88;		// short applet/PSBT.current_output_map
					sconst_0;
					putstatic_s 85;		// short applet/PSBT.byte_size
					return;
		}

	}

	.class public PSBTKey 10 extends 0.0 {		// extends java/lang/Object

		.fields {
			public short start 0;		// S
			public short key_len 1;		// S
			public short key_len_bytes 2;		// S
			public short keyKype 3;		// S
		}

		.publicMethodTable 1 {
			equals(Ljava/lang/Object;)Z;
			fill(S)V;
			getSize()S;
			reset()V;
		}

		.packageMethodTable 0 {
		}

		.method public <init>()V 0 {
			.stack 2;
			.locals 0;

				L0:	aload_0;
					invokespecial 57;		// java/lang/Object.<init>()V
					sconst_m1;
					putfield_s_this 5;		// short applet/PSBTKey.start
					sconst_m1;
					putfield_s_this 39;		// short applet/PSBTKey.key_len
					sconst_1;
					putfield_s_this 40;		// short applet/PSBTKey.key_len_bytes
					sconst_m1;
					putfield_s_this 16;		// short applet/PSBTKey.keyKype
					return;
		}

		.method public fill(S)V 1 {
			.stack 3;
			.locals 0;

				L0:	sload_1;
					putfield_s_this 5;		// short applet/PSBTKey.start
					aload_0;
					getfield_s_this 5;		// short applet/PSBTKey.start
					invokestatic 52;		// applet/Tools.compactWeirdoInt(S)S
					putfield_s 39;		// short applet/PSBTKey.key_len
					getfield_s_this 39;		// short applet/PSBTKey.key_len
					sspush 253;
					if_scmplt L2;
				L1:	sconst_3;
					putfield_s_this 40;		// short applet/PSBTKey.key_len_bytes
				L2:	aload_0;
					getfield_s_this 5;		// short applet/PSBTKey.start
					getfield_s_this 40;		// short applet/PSBTKey.key_len_bytes
					sadd;
					invokestatic 52;		// applet/Tools.compactWeirdoInt(S)S
					putfield_s 16;		// short applet/PSBTKey.keyKype
					return;
		}

		.method public getSize()S 2 {
			.stack 2;
			.locals 0;

				L0:	getfield_s_this 40;		// short applet/PSBTKey.key_len_bytes
					getfield_s_this 39;		// short applet/PSBTKey.key_len
					sadd;
					sreturn;
		}

		.method public reset()V 3 {
			.stack 2;
			.locals 0;

				L0:	sconst_m1;
					putfield_s_this 5;		// short applet/PSBTKey.start
					sconst_m1;
					putfield_s_this 39;		// short applet/PSBTKey.key_len
					sconst_1;
					putfield_s_this 40;		// short applet/PSBTKey.key_len_bytes
					sconst_m1;
					putfield_s_this 16;		// short applet/PSBTKey.keyKype
					return;
		}

	}

	.class public PSBTKeyPair 11 extends 0.0 {		// extends java/lang/Object

		.fields {
			public short start 0;		// S
			public PSBTKey key 1;		// Lapplet/PSBTKey;
			public PSBTValue value 2;		// Lapplet/PSBTValue;
		}

		.publicMethodTable 1 {
			equals(Ljava/lang/Object;)Z;
			fill(S)V;
			getSize()S;
			reset()V;
		}

		.packageMethodTable 0 {
		}

		.method public <init>()V 0 {
			.stack 3;
			.locals 0;

				L0:	aload_0;
					invokespecial 57;		// java/lang/Object.<init>()V
					sconst_m1;
					putfield_s_this 41;		// short applet/PSBTKeyPair.start
					aload_0;
					new 115;		// applet/PSBTKey
					dup;
					invokespecial 116;		// applet/PSBTKey.<init>()V
					putfield_a 4;		// reference applet/PSBTKeyPair.key
					aload_0;
					new 117;		// applet/PSBTValue
					dup;
					invokespecial 118;		// applet/PSBTValue.<init>()V
					putfield_a 17;		// reference applet/PSBTKeyPair.value
					return;
		}

		.method public fill(S)V 1 {
			.stack 3;
			.locals 0;

				L0:	sload_1;
					putfield_s_this 41;		// short applet/PSBTKeyPair.start
					getfield_a_this 4;		// reference applet/PSBTKeyPair.key
					sload_1;
					invokevirtual 119;		// fill(S)V
					getfield_a_this 17;		// reference applet/PSBTKeyPair.value
					sload_1;
					getfield_a_this 4;		// reference applet/PSBTKeyPair.key
					invokevirtual 120;		// getSize()S
					sadd;
					invokevirtual 121;		// fill(S)V
					return;
		}

		.method public getSize()S 2 {
			.stack 2;
			.locals 0;

				L0:	getfield_a_this 4;		// reference applet/PSBTKeyPair.key
					invokevirtual 120;		// getSize()S
					getfield_a_this 17;		// reference applet/PSBTKeyPair.value
					invokevirtual 122;		// getSize()S
					sadd;
					sreturn;
		}

		.method public reset()V 3 {
			.stack 2;
			.locals 0;

				L0:	getfield_a_this 4;		// reference applet/PSBTKeyPair.key
					invokevirtual 123;		// reset()V
					getfield_a_this 17;		// reference applet/PSBTKeyPair.value
					invokevirtual 124;		// reset()V
					sconst_m1;
					putfield_s_this 41;		// short applet/PSBTKeyPair.start
					return;
		}

	}

	.class public PSBTValue 12 extends 0.0 {		// extends java/lang/Object

		.fields {
			public short start 0;		// S
			public short value_len 1;		// S
			public short value_len_bytes 2;		// S
		}

		.publicMethodTable 1 {
			equals(Ljava/lang/Object;)Z;
			fill(S)V;
			getSize()S;
			getByte(S)B;
			reset()V;
		}

		.packageMethodTable 0 {
		}

		.method public <init>()V 0 {
			.stack 2;
			.locals 0;

				L0:	aload_0;
					invokespecial 57;		// java/lang/Object.<init>()V
					sconst_m1;
					putfield_s_this 42;		// short applet/PSBTValue.start
					sconst_m1;
					putfield_s_this 43;		// short applet/PSBTValue.value_len
					sconst_1;
					putfield_s_this 18;		// short applet/PSBTValue.value_len_bytes
					return;
		}

		.method public fill(S)V 1 {
			.stack 2;
			.locals 0;

				L0:	sload_1;
					putfield_s_this 42;		// short applet/PSBTValue.start
					aload_0;
					getfield_s_this 42;		// short applet/PSBTValue.start
					invokestatic 52;		// applet/Tools.compactWeirdoInt(S)S
					putfield_s 43;		// short applet/PSBTValue.value_len
					getfield_s_this 43;		// short applet/PSBTValue.value_len
					sspush 253;
					if_scmplt L2;
				L1:	sconst_3;
					putfield_s_this 18;		// short applet/PSBTValue.value_len_bytes
				L2:	return;
		}

		.method public getSize()S 2 {
			.stack 2;
			.locals 0;

				L0:	getfield_s_this 18;		// short applet/PSBTValue.value_len_bytes
					getfield_s_this 43;		// short applet/PSBTValue.value_len
					sadd;
					sreturn;
		}

		.method public getByte(S)B 3 {
			.stack 3;
			.locals 0;

				L0:	getstatic_a 95;		// reference applet/MainApplet.PSBTdata
					getfield_s_this 42;		// short applet/PSBTValue.start
					getfield_s_this 18;		// short applet/PSBTValue.value_len_bytes
					sadd;
					sload_1;
					sadd;
					baload;
					sreturn;
		}

		.method public reset()V 4 {
			.stack 2;
			.locals 0;

				L0:	sconst_m1;
					putfield_s_this 42;		// short applet/PSBTValue.start
					sconst_m1;
					putfield_s_this 43;		// short applet/PSBTValue.value_len
					sconst_1;
					putfield_s_this 18;		// short applet/PSBTValue.value_len_bytes
					return;
		}

	}

	.class public Policy 13 extends 0.0 {		// extends java/lang/Object

		.fields {
			public static final byte minTotalOutput = 0;		// B
			public static final byte maxTotalOutput = 1;		// B
			public static final byte minOutputWithSigScr = 2;		// B
			public static final byte maxOutputWithSigScr = 3;		// B
			public static final byte minNumberofInputs = 4;		// B
			public static final byte maxNumberofInputs = 5;		// B
			public static final byte minNumberofOutputs = 6;		// B
			public static final byte maxNumberofOutputs = 7;		// B
			public static final byte signedPSBT = 8;		// B
			public static final byte signedTimeLapse = 9;		// B
			public static final byte checkSecret = 10;		// B
			public static final byte transactionVersion = 12;		// B
			public static final byte policyAnd = 13;		// B
		}

		.publicMethodTable 1 {
			equals(Ljava/lang/Object;)Z;
		}

		.packageMethodTable 0 {
		}

		.method public <init>()V 0 {
			.stack 1;
			.locals 0;

				L0:	aload_0;
					invokespecial 57;		// java/lang/Object.<init>()V
					return;
		}

		.method public static validateTotalOutput(BS)Z 1 {
			.stack 5;
			.locals 0;

				L0:	getstatic_a 69;		// reference applet/MainApplet.privDataStorage
					sload_0;
					aaload;
					getfield_a 0;		// reference applet/ArrayInDisguise.array
					sconst_0;
					getstatic_a 73;		// reference applet/MainApplet.totalOutput
					sconst_0;
					bspush 8;
					invokestatic 127;		// applet/Tools.littleEndianCompareArrays([BS[BSS)S
					sload_1;
					if_scmpeq L2;
				L1:	sconst_1;
					goto L3;
				L2:	sconst_0;
				L3:	sreturn;
		}

		.method public static validateValueOwSS(BBS)Z 2 {
			.stack 5;
			.locals 5;

				L0:	sconst_0;
					sstore_3;
					sconst_0;
					sstore 4;
					getstatic_s 86;		// short applet/GlobalMap.PSBTversion
					ifne L6;
				L1:	sconst_0;
					sstore 5;
				L2:	sload 5;
					getstatic_a 67;		// reference applet/MainApplet.psbt
					getfield_a 34;		// reference applet/PSBT.globalMap
					getfield_a 15;		// reference applet/GlobalMap.globalUnsignedTX
					getfield_s 24;		// short applet/GlobalUnsignedTX.output_count
					if_scmpge L6;
				L3:	getstatic_a 67;		// reference applet/MainApplet.psbt
					getfield_a 34;		// reference applet/PSBT.globalMap
					getfield_a 15;		// reference applet/GlobalMap.globalUnsignedTX
					getfield_a 25;		// reference applet/GlobalUnsignedTX.outputs
					sload 5;
					aaload;
					getfield_s 8;		// short applet/GlobalUnsignedTXOutput.valueStart
					sstore 4;
					getstatic_a 67;		// reference applet/MainApplet.psbt
					getfield_a 34;		// reference applet/PSBT.globalMap
					getfield_a 15;		// reference applet/GlobalMap.globalUnsignedTX
					getfield_a 25;		// reference applet/GlobalUnsignedTX.outputs
					sload 5;
					aaload;
					getfield_s 33;		// short applet/GlobalUnsignedTXOutput.script_pub_key_start
					sstore_3;
					sload_0;
					sload 4;
					sload_1;
					sload_3;
					sload_2;
					invokestatic 128;		// applet/Policy.checkItself(BSBSS)Z
					ifeq L5;
				L4:	sconst_1;
					sreturn;
				L5:	sinc 5 1;
					goto L2;
				L6:	getstatic_s 86;		// short applet/GlobalMap.PSBTversion
					sconst_2;
					if_scmpne L19;
				L7:	sconst_0;
					sstore 5;
				L8:	sload 5;
					getstatic_a 67;		// reference applet/MainApplet.psbt
					getfield_a 34;		// reference applet/PSBT.globalMap
					getfield_s 14;		// short applet/GlobalMap.outputMapsTotal
					if_scmpge L19;
				L9:	sconst_0;
					sstore 7;
				L10:	sload 7;
					getstatic_a 67;		// reference applet/MainApplet.psbt
					getfield_a 36;		// reference applet/PSBT.outputMaps
					sload 5;
					aaload;
					getfield_s 11;		// short applet/GeneralMap.currentKeyPair
					if_scmpge L16;
				L11:	getstatic_a 67;		// reference applet/MainApplet.psbt
					getfield_a 36;		// reference applet/PSBT.outputMaps
					sload 5;
					aaload;
					getfield_a 12;		// reference applet/GeneralMap.keyPairs
					sload 7;
					aaload;
					getfield_a 4;		// reference applet/PSBTKeyPair.key
					getfield_s 16;		// short applet/PSBTKey.keyKype
					sstore 6;
					sload 6;
					sconst_3;
					if_scmpne L13;
				L12:	getstatic_a 67;		// reference applet/MainApplet.psbt
					getfield_a 36;		// reference applet/PSBT.outputMaps
					sload 5;
					aaload;
					getfield_a 12;		// reference applet/GeneralMap.keyPairs
					sload 7;
					aaload;
					getfield_a 17;		// reference applet/PSBTKeyPair.value
					getfield_s 42;		// short applet/PSBTValue.start
					sstore 4;
				L13:	sload 6;
					sconst_4;
					if_scmpne L15;
				L14:	getstatic_a 67;		// reference applet/MainApplet.psbt
					getfield_a 36;		// reference applet/PSBT.outputMaps
					sload 5;
					aaload;
					getfield_a 12;		// reference applet/GeneralMap.keyPairs
					sload 7;
					aaload;
					getfield_a 17;		// reference applet/PSBTKeyPair.value
					getfield_s 42;		// short applet/PSBTValue.start
					sstore_3;
				L15:	sinc 7 1;
					goto L10;
				L16:	sload_0;
					sload 4;
					sload_1;
					sload_3;
					sload_2;
					invokestatic 128;		// applet/Policy.checkItself(BSBSS)Z
					ifeq L18;
				L17:	sconst_1;
					sreturn;
				L18:	sinc 5 1;
					goto L8;
				L19:	sconst_0;
					sreturn;
		}

		.method static checkItself(BSBSS)Z {
			.stack 6;
			.locals 0;

				L0:	getstatic_a 69;		// reference applet/MainApplet.privDataStorage
					sload_0;
					aaload;
					getfield_a 0;		// reference applet/ArrayInDisguise.array
					sconst_0;
					getstatic_a 95;		// reference applet/MainApplet.PSBTdata
					sload_1;
					getstatic_a 69;		// reference applet/MainApplet.privDataStorage
					sload_0;
					aaload;
					getfield_s 1;		// short applet/ArrayInDisguise.offset
					sspush 255;
					sand;
					invokestatic 127;		// applet/Tools.littleEndianCompareArrays([BS[BSS)S
					sload 4;
					if_scmpeq L3;
				L1:	getstatic_a 69;		// reference applet/MainApplet.privDataStorage
					sload_2;
					aaload;
					getfield_a 0;		// reference applet/ArrayInDisguise.array
					sconst_0;
					getstatic_a 95;		// reference applet/MainApplet.PSBTdata
					sload_3;
					bspush 8;
					invokestatic 101;		// javacard/framework/Util.arrayCompare([BS[BSS)B
					ifne L3;
				L2:	sconst_1;
					goto L4;
				L3:	sconst_0;
				L4:	sreturn;
		}

	}

	.class public SecP256k1 14 extends 0.0 {		// extends java/lang/Object

		.fields {
			public static final byte[] p 0 = {-1,-1,-1,-1,-1,-1,-1,-1,-1,-1,-1,-1,-1,-1,-1,-1,-1,-1,-1,-1,-1,-1,-1,-1,-1,-1,-1,-2,-1,-1,-4,47};		// [B
			public static final byte[] a 1 = {0,0,0,0,0,0,0,0,0,0,0,0,0,0,0,0,0,0,0,0,0,0,0,0,0,0,0,0,0,0,0,0};		// [B
			public static final byte[] b 2 = {0,0,0,0,0,0,0,0,0,0,0,0,0,0,0,0,0,0,0,0,0,0,0,0,0,0,0,0,0,0,0,7};		// [B
			public static final byte[] G 3 = {4,121,-66,102,126,-7,-36,-69,-84,85,-96,98,-107,-50,-121,11,7,2,-101,-4,-37,45,-50,40,-39,89,-14,-127,91,22,-8,23,-104,72,58,-38,119,38,-93,-60,101,93,-92,-5,-4,14,17,8,-88,-3,23,-76,72,-90,-123,84,25,-100,71,-48,-113,-5,16,-44,-72};		// [B
			public static final byte[] r 4 = {-1,-1,-1,-1,-1,-1,-1,-1,-1,-1,-1,-1,-1,-1,-1,-2,-70,-82,-36,-26,-81,72,-96,59,-65,-46,94,-116,-48,54,65,65};		// [B
		}

		.publicMethodTable 1 {
			equals(Ljava/lang/Object;)Z;
		}

		.packageMethodTable 0 {
		}

		.method public <init>()V 0 {
			.stack 1;
			.locals 0;

				L0:	aload_0;
					invokespecial 57;		// java/lang/Object.<init>()V
					return;
		}

	}

	.class public SetAndVerify 15 extends 0.0 {		// extends java/lang/Object

		.fields {
			static 2.19 publicKey;		// Ljavacard/security/ECPublicKey;
			static 2.15 signEngine;		// Ljavacard/security/Signature;
		}

		.publicMethodTable 1 {
			equals(Ljava/lang/Object;)Z;
		}

		.packageMethodTable 0 {
		}

		.method public <init>()V 0 {
			.stack 1;
			.locals 0;

				L0:	aload_0;
					invokespecial 57;		// java/lang/Object.<init>()V
					return;
		}

		.method public static setPublicKey([BS)V 1 {
			.stack 4;
			.locals 0;

				L0:	bspush 11;
					sspush 256;
					sconst_0;
					invokestatic 129;		// javacard/security/KeyBuilder.buildKey(BSZ)Ljavacard/security/Key;
					checkcast 0 130;		// T_CLASSORINTERFACE javacard/security/ECPublicKey
					putstatic_a 131;		// reference applet/SetAndVerify.publicKey
					bspush 17;
					sconst_0;
					invokestatic 132;		// javacard/security/Signature.getInstance(BZ)Ljavacard/security/Signature;
					putstatic_a 133;		// reference applet/SetAndVerify.signEngine
					getstatic_a 131;		// reference applet/SetAndVerify.publicKey
					getstatic_a 134;		// reference applet/SecP256k1.p
					sconst_0;
					getstatic_a 134;		// reference applet/SecP256k1.p
					arraylength;
					invokeinterface 4 130 4;		// javacard/security/ECPublicKey
					getstatic_a 131;		// reference applet/SetAndVerify.publicKey
					getstatic_a 135;		// reference applet/SecP256k1.a
					sconst_0;
					getstatic_a 135;		// reference applet/SecP256k1.a
					arraylength;
					invokeinterface 4 130 7;		// javacard/security/ECPublicKey
					getstatic_a 131;		// reference applet/SetAndVerify.publicKey
					getstatic_a 136;		// reference applet/SecP256k1.b
					sconst_0;
					getstatic_a 136;		// reference applet/SecP256k1.b
					arraylength;
					invokeinterface 4 130 8;		// javacard/security/ECPublicKey
					getstatic_a 131;		// reference applet/SetAndVerify.publicKey
					getstatic_a 137;		// reference applet/SecP256k1.G
					sconst_0;
					getstatic_a 137;		// reference applet/SecP256k1.G
					arraylength;
					invokeinterface 4 130 9;		// javacard/security/ECPublicKey
					getstatic_a 131;		// reference applet/SetAndVerify.publicKey
					getstatic_a 138;		// reference applet/SecP256k1.r
					sconst_0;
					getstatic_a 138;		// reference applet/SecP256k1.r
					arraylength;
					invokeinterface 4 130 10;		// javacard/security/ECPublicKey
					getstatic_a 131;		// reference applet/SetAndVerify.publicKey
					sconst_1;
					invokeinterface 2 130 11;		// javacard/security/ECPublicKey
					getstatic_a 131;		// reference applet/SetAndVerify.publicKey
					aload_0;
					sconst_0;
					sload_1;
					invokeinterface 4 130 18;		// javacard/security/ECPublicKey
					return;
		}

		.method public static verifyECDSA([BS[BS)Z 2 {
			.stack 7;
			.locals 0;

				L0:	getstatic_a 133;		// reference applet/SetAndVerify.signEngine
					getstatic_a 131;		// reference applet/SetAndVerify.publicKey
					sconst_2;
					invokevirtual 139;		// init(Ljavacard/security/Key;B)V
					getstatic_a 133;		// reference applet/SetAndVerify.signEngine
					aload_0;
					sconst_0;
					sload_1;
					aload_2;
					sconst_0;
					sload_3;
					invokevirtual 140;		// verify([BSS[BSS)Z
					sreturn;
		}

	}

	.class public Tools 16 extends 0.0 {		// extends java/lang/Object

		.publicMethodTable 1 {
			equals(Ljava/lang/Object;)Z;
		}

		.packageMethodTable 0 {
		}

		.method public <init>()V 0 {
			.stack 1;
			.locals 0;

				L0:	aload_0;
					invokespecial 57;		// java/lang/Object.<init>()V
					return;
		}

		.method public static compactWeirdoInt(S)S 1 {
			.stack 4;
			.locals 0;

				L0:	getstatic_a 95;		// reference applet/MainApplet.PSBTdata
					sload_0;
					baload;
					sspush 255;
					sand;
					sspush 253;
					if_scmpne L2;
				L1:	getstatic_a 95;		// reference applet/MainApplet.PSBTdata
					sload_0;
					sconst_1;
					sadd;
					baload;
					sspush 255;
					sand;
					bspush 8;
					sshl;
					getstatic_a 95;		// reference applet/MainApplet.PSBTdata
					sload_0;
					sconst_2;
					sadd;
					baload;
					sspush 255;
					sand;
					sor;
					sreturn;
				L2:	getstatic_a 95;		// reference applet/MainApplet.PSBTdata
					sload_0;
					baload;
					sspush 255;
					sand;
					sreturn;
		}

		.method public static byteSizeOfCWI(S)S 2 {
			.stack 2;
			.locals 0;

				L0:	sload_0;
					sspush 253;
					if_scmpge L2;
				L1:	sconst_1;
					sreturn;
				L2:	sconst_3;
					sreturn;
		}

		.method public static littleEndianCompareArrays([BS[BSS)S 3 {
			.stack 4;
			.locals 1;

				L0:	sconst_1;
					sstore 5;
				L1:	sload 5;
					sload 4;
					if_scmpgt L7;
				L2:	aload_0;
					sload_1;
					sload 4;
					sadd;
					sload 5;
					ssub;
					baload;
					sspush 255;
					sand;
					aload_2;
					sload_3;
					sload 4;
					sadd;
					sload 5;
					ssub;
					baload;
					sspush 255;
					sand;
					if_scmple L4;
				L3:	sconst_1;
					sreturn;
				L4:	aload_0;
					sload_1;
					sload 4;
					sadd;
					sload 5;
					ssub;
					baload;
					sspush 255;
					sand;
					aload_2;
					sload_3;
					sload 4;
					sadd;
					sload 5;
					ssub;
					baload;
					sspush 255;
					sand;
					if_scmpge L6;
				L5:	sconst_m1;
					sreturn;
				L6:	sinc 5 1;
					goto L1;
				L7:	sconst_0;
					sreturn;
		}

		.method public static getTotalOutput()V 4 {
			.stack 4;
			.locals 3;

				L0:	sconst_0;
					sstore_0;
					getstatic_s 86;		// short applet/GlobalMap.PSBTversion
					ifne L3;
				L1:	sload_0;
					getstatic_a 67;		// reference applet/MainApplet.psbt
					getfield_a 34;		// reference applet/PSBT.globalMap
					getfield_a 15;		// reference applet/GlobalMap.globalUnsignedTX
					getfield_s 24;		// short applet/GlobalUnsignedTX.output_count
					if_scmpge L3;
				L2:	getstatic_a 73;		// reference applet/MainApplet.totalOutput
					getstatic_a 95;		// reference applet/MainApplet.PSBTdata
					getstatic_a 67;		// reference applet/MainApplet.psbt
					getfield_a 34;		// reference applet/PSBT.globalMap
					getfield_a 15;		// reference applet/GlobalMap.globalUnsignedTX
					getfield_a 25;		// reference applet/GlobalUnsignedTX.outputs
					sload_0;
					aaload;
					getfield_s 8;		// short applet/GlobalUnsignedTXOutput.valueStart
					invokestatic 141;		// applet/Tools.satoshisPlusLE([B[BS)V
					sinc 0 1;
					goto L1;
				L3:	getstatic_s 86;		// short applet/GlobalMap.PSBTversion
					sconst_2;
					if_scmpne L11;
				L4:	sload_0;
					getstatic_a 67;		// reference applet/MainApplet.psbt
					getfield_a 34;		// reference applet/PSBT.globalMap
					getfield_s 14;		// short applet/GlobalMap.outputMapsTotal
					if_scmpge L11;
				L5:	sconst_0;
					sstore_2;
				L6:	sload_2;
					getstatic_a 67;		// reference applet/MainApplet.psbt
					getfield_a 36;		// reference applet/PSBT.outputMaps
					sload_0;
					aaload;
					getfield_s 11;		// short applet/GeneralMap.currentKeyPair
					if_scmpge L10;
				L7:	getstatic_a 67;		// reference applet/MainApplet.psbt
					getfield_a 36;		// reference applet/PSBT.outputMaps
					sload_0;
					aaload;
					getfield_a 12;		// reference applet/GeneralMap.keyPairs
					sload_2;
					aaload;
					getfield_a 4;		// reference applet/PSBTKeyPair.key
					getfield_s 16;		// short applet/PSBTKey.keyKype
					sstore_1;
					sload_1;
					sconst_3;
					if_scmpne L9;
				L8:	getstatic_a 73;		// reference applet/MainApplet.totalOutput
					getstatic_a 95;		// reference applet/MainApplet.PSBTdata
					getstatic_a 67;		// reference applet/MainApplet.psbt
					getfield_a 36;		// reference applet/PSBT.outputMaps
					sload_0;
					aaload;
					getfield_a 12;		// reference applet/GeneralMap.keyPairs
					sload_2;
					aaload;
					getfield_a 17;		// reference applet/PSBTKeyPair.value
					getfield_s 42;		// short applet/PSBTValue.start
					invokestatic 141;		// applet/Tools.satoshisPlusLE([B[BS)V
				L9:	sinc 2 1;
					goto L6;
				L10:	sinc 0 1;
					goto L4;
				L11:	return;
		}

		.method public static satoshisPlusLE([B[BS)V 5 {
			.stack 6;
			.locals 1;

				L0:	bspush 7;
					sstore_3;
				L1:	sload_3;
					iflt L6;
				L2:	aload_0;
					sload_3;
					baload;
					sspush 255;
					sand;
					aload_1;
					sload_2;
					sload_3;
					sadd;
					baload;
					sspush 255;
					sand;
					sadd;
					sspush 255;
					if_scmple L4;
				L3:	aload_0;
					sload_3;
					aload_0;
					sload_3;
					baload;
					sspush 255;
					sand;
					aload_1;
					sload_2;
					sload_3;
					sadd;
					baload;
					sspush 255;
					sand;
					sadd;
					s2b;
					bastore;
					aload_0;
					sload_3;
					sconst_1;
					ssub;
					dup2;
					baload;
					sconst_1;
					sadd;
					s2b;
					bastore;
					goto L5;
				L4:	aload_0;
					sload_3;
					aload_0;
					sload_3;
					baload;
					sspush 255;
					sand;
					aload_1;
					sload_2;
					sload_3;
					sadd;
					baload;
					sspush 255;
					sand;
					sadd;
					s2b;
					bastore;
				L5:	sinc 3 -1;
					goto L1;
				L6:	return;
		}

	}

}
